{"4H015c": "新增: 背", "4H0ZPt": "元兴元年（402年），孙恩再攻临海，被击败赴海自杀。其妹夫卢循继领其众（111-104）。卢循转战岭南，攻占广州，后率军北上进攻建康，被刘裕击败。义熙七年（411年），卢循兵败投水自杀，起义最终失败。", "4H0mgH": "> 到彦之至马头，何承天自归。彦之因监荆州府事，以周超为参军。", "4H0uhW": "新增词条：天下兵马元帅（历任官员表格）", "4H1N3y": "| [[周岳]] | （258-082） | 以[[武安节度使]][[周岳]]为岭南西道节度使。 |", "4H1uc1": "编辑: 无盐", "4H22CS": "[[乐毅伐齐]]，中军据[[临淄]]而镇齐都（004-053）。[[秦始皇]][[病甚]]，乃令中军府令行[[符玺]]事[[赵高]]为书赐[[扶苏]]（007-070）。[[荀悦]]论《[[春秋]]》之义，舍中军则善之（029-078）。", "4H26ay": "id: 堂", "4H2c3T": "**疆域**为疆界与领土之合称，国家版图之范围。", "4H2cA8": "周人寇晋阳，段韶以逸待劳：", "4H2eI0": "id: 百里洲", "4H2hny": "label: 官吏", "4H2yaH": "新增: 荀恺", "4H2zdt": "张奂，字然明，敦煌人。东汉北中郎将，以平定东羌、匈奴功著。与皇甫规、段颎并称凉州三明。", "4H4Xhl": "[[魏主]]伐[[统万]]，命长孙翰等将三[[万骑]]为[[前驱]]。及夏主[[出战]]，长孙翰等言：\"夏兵步陈难陷，宜避其锋。\"[[魏主]]不听，从之[[决战]]（120-122）。长孙翰将八千骑追夏主至[[高平]]，不及而还（120-123）。", "4H5Mlq": "# 胡骑", "4H5yZR": "# 宇文弼", "4H60oc": "[[赵充国]][[上书]]分析[[羌人]][[形势]]，提出[[屯田]]之策。认为\"[[羌人]]易制，以其种自有豪，数相攻击\"，宜分化[[瓦解]]，以[[屯田]]坐困[[羌人]]。[[汉宣帝]]从其计（026-028）。", "4H64dk": "description: 唐代名将，筑三受降城防御突厥", "4H6l4t": "[078-065] 吴人以蜀初亡，交趾携叛，国内恐惧，欲得长君。左典军万尝为乌程令，与乌程侯皓相善，称“皓才识明断，长沙桓王之俦也；又加之好学，奉遵法度。”屡言之于丞相兴、左将军布，兴、布说硃太后，欲以皓为嗣。硃后曰：“我寡妇人，安知社稷之虑，苟吴国无陨，宗庙有赖，可矣。”于是遂迎立皓，改元元兴，大赦。", "4H6t6s": "# 泥溪", "4H7vu9": "id: 战_(概念)", "4H8EdU": "[095-079] 九月，赵王虎迁都于鄴，大赦。", "4H8OzQ": "| 452 | 济南太守申坦等当西道 | （126-056） |", "4H8Yz8": "**唐临**，唐大理卿。右卫率府铠[[曹参]]军唐临出为万泉丞，县有系囚十许人，会春雨，临纵之，使归[[耕种]]，皆如期而返（191-141）。[[治书侍御史]]唐临追劾[[长孙无忌]]之罪（197-036）。[[李世民|唐太宗]]问大理卿唐临系囚之数，对曰：\"见囚五十馀人，唯二人应死。\"上悦。上尝录系囚，前卿所处者多号呼称冤，临所处者独无言（199-058）。后[[吏部尚书]]唐临为许祎、张伦[[授官]]，被劾为挟私（200-070）。", "4H9JYM": "索元礼，武周酷吏。[[《资治通鉴》]]载索元礼以告密受武则天擢用，主制狱，性极残忍。", "4H9QCl": "光武招怀南虏以御北狄：", "4HA68n": "鸿门宴是中国历史上最著名的政治危机之一，项羽的优柔寡断与\"妇人之仁\"成为其最终失败的重要诠释。后人以\"项庄舞剑，意在沛公\"为成语，以\"人为刀俎，我为鱼肉\"描述险境，皆出于此役的记载。", "4HABIF": "[[苏峻]]之乱，宣城[[内史]]桓彝闻京城不守，慷慨流涕，进屯[[泾县]]（094-034）。裨惠劝彝宜且与[[苏峻]][[通使]]以纾交至之祸，彝曰：\"吾受国厚恩，义在致死，焉能忍耻与逆臣通问！\"其志节如此。桓彝尝谓[[谢安#谢尚|名士]]：\"季野有皮里《[[春秋]]》。\"言其外无[[臧否]]而内有[[褒贬]]（095-054）。", "4HB0VZ": "持续臣附朝廷，\"加武顺军[[节度使]][[王镕|赵王]][[王镕]]宁太师，天雄[[节度使]]鄴王[[罗绍威]]守[[太傅]]，义武[[节度使]]【王处直】兼[[侍中]]\"（266-029），在各藩镇中获得较高地位。", "4HBEpr": "**优**，优伶、俳优。倡优下贱得为后饰为汉初僭越之甚，东方朔枚皋以俳优畜之终不任以事。", "4HBFXF": "[[智伯]]以[[絺疵]]之言告二子（001-011）。[[公叔痤]]告[[商鞅|卫鞅]]速行免祸（002-018）。告奸者与斩敌首同赏（002-020）。公子虔之徒告[[商鞅|商君]]欲反（002-073）。[[巴蜀]]相攻击俱[[告急]]于秦（003-016）。", "4HBYAr": "[[隋文帝]]悉召[[流人]]，令携负[[妻子]]俱入，赐宴于殿庭而赦之（179-040）。[[唐太宗]]赐宴于芳兰殿，命有司厚加给待，每五日一会（198-066）。[[唐玄宗]]上皇常于[[长庆]]楼置[[酒食]]赐[[父老]]，又尝召[[将军]]郭英乂等上楼赐宴（221-081）。", "4HBunh": "掖人苏峻帅乡里数千家结垒以自保，远近多附之。曹嶷恶其强，将攻之，峻帅众浮海来奔。帝以峻为鹰扬将军（091-003）。王敦反，诏征苏峻等入卫京师（093-011）。苏峻等帅精卒万人至，帝夜见劳之（093-021）。庾亮督苏峻等追沈充于吴兴（093-023）。", "4HCdAc": "> 帝既施惠天下，诸侯、四夷远近欢洽。乃修代来功，封【宋昌】为壮[[诸葛亮|武侯]]。", "4HCzye": "| 558 | 骠骑大将军高归彦为尚书左仆射。 | （167-077） |", "4HD2U9": "> 冬，上南巡狩，至于盛唐，望祀虞舜于九疑。登灊天柱山，自寻阳浮江，亲射蛟江中，获之。舳舻千里，薄枞阳而出，遂北至琅邪，并海，所过礼祠其名山大川。春，三月，还至太山，增封。甲子，始祀上帝于明堂，配以[[汉高祖刘邦|高祖]]，因朝诸侯王、列侯，受郡、国计。夏，四月，赦天下，所幸县毋出今年租赋。还，幸甘泉，郊泰畤。", "4HDB7Y": "> （034-016）", "4HEFPZ": "| **西元** | 公元940年 |", "4HEKDy": "尚书郎以令史久次补之，光武帝始用孝廉为尚书郎（040-043）。尚书郎南阳樊准以儒风浸衰上疏（049-027）。尚书郎张俊有私书与袁敞子，敞坐策免，俊下狱死（050-021）。", "4HFKn5": "羌是古代西部民族，与[[中原]]政权长期并存。[[西汉]][[隋文帝|文帝]]时羌道、[[武都]]道[[山崩]]（013-011）。[[司马相如]]谕蜀文以\"羌、僰\"并举，言[[武帝]]开[[西南夷]]之事（018-055）。[[羌人]]屡为汉[[边患]]，汉设护羌[[校尉]]以统之。", "4HFyH0": "- 秦孝王俊久疾，[[隋文帝]][[遣使]]（179-009）", "4HGpLk": "tags: [唐, 节度使, 山南西道, 宪宗]", "4HHHG3": "**给事中**为加官名，掌顾问应对、侍从左右。秦汉时以[[大夫]]、[[博士]]等加给事中衔，得以出入[[禁中]]，参与机要。", "4HHMqA": "pn_prefix: \"200\"", "4HHXVS": "> 记室薛收……并以本官兼文学馆学士，分为三番，更日直宿。", "4HI1Hp": "**劫盗**指抢劫财物的[[盗贼]]，为古代[[社会]]治安的主要威胁。", "4HI3XC": "栾大，[[西汉]][[方士]]，[[胶东]]康王[[刘寄]]之臣。以[[神仙]][[术数|方术]]得幸于[[汉武帝]]，封五利将军、乐通侯，后因[[术数|方术]]不验被诛。", "4HI5A1": "> 今二宫危逼，猾寇滔天，臣子当戮力同心，岂可自相矛盾！", "4HIT26": "755年[[安禄山]]以[[范阳]]、平卢、[[河东]]三镇[[魏博节度使|节度使]]身份起兵，是为[[安史之乱]]。乱后，各[[地节]]度使拥兵自重，[[朝廷]]无力节制，形成\"藩镇[[割据]]\"局面。[[唐朝]]虽延续百年，实已[[名存实亡]]。", "4HIXsS": "[[豫让]]诈为刑人入[[赵襄子]][[宫中]]涂厕（001-014）。[[商鞅]]筑冀阙宫庭于[[咸阳]][[徙都]]之（002-049）。[[苏秦]]说[[齐王]]高[[宫室]]大[[苑囿]]以敝齐（002-120）。[[燕昭王]]为[[郭隗]]改筑宫而师事之（003-032）。[[张仪]]说[[楚王]][[鸿台]]之宫桑林之宛非王所有（003-036）。武灵王[[大朝]][[东宫]]传国于何（003-083）。始皇作[[宫室]][[咸阳]]北阪上殿屋[[复道]]周阁相属（007-036）。", "4HJRl3": "[190-002] [[汉高祖刘邦|高祖]]神尧大圣光孝皇帝中之下武德五年（壬午，公元六二二年）", "4HJsQD": "[204-092] 九月，丙子，侍御史汲人傅游艺帅关中百姓九百馀人诣阙上表，请改国号曰周，赐皇帝姓武氏，太后不许；擢游艺为给事中。于是百官及帝室宗戚、远近百姓、四夷酋长、沙门、道士合六万馀人，俱上表如游艺所请，皇帝亦上表自请赐姓武氏。戊寅，群臣上言：“有凤皇自明堂飞入上阳宫，还集左台梧桐之上，久之，飞东南去；及赤雀数万集朝堂。", "4HK1x0": "# [[前287年]]", "4HKAah": "\"鬲\"在《[[资治通鉴]]》指阻隔，也作地名。匈奴右方居盐泽以东至陇西长城南接羌鬲汉道焉（019-039）。亲戚之路鬲塞而不通（022-050）。鬲县五姓共逐守长据城而反（041-030）。鬲侯硃祜薨（044-010）。肝鬲之要也（066-016）。", "4HKUdx": "代宗时又设诸道税钱使，专门管理青苗钱的征收。后青苗钱与其他税种合并管理，成为[[唐朝|唐代]]附加税体系的一部分。", "4HKlN0": "[[元嘉北伐]]期间，王玄谟为东路大[[军主]]帅，围[[滑台]]数月不下：", "4HNdtG": "ji: \"唐纪七十\"", "4HODd1": "魏以[[韩麒麟]]为[[齐州刺史]]（135-175）。齐州频[[岁饥]]疫（136-080）。", "4HObL2": "> （116-071）", "4HPGVA": "[[吐蕃]]入[[长安]]，立故邠王守礼之孙广[[周武王|武王]]李承宏为帝，[[改元]]，置百官（223-014）。", "4HPqSd": "> 齐主出畋，有兔惊马，坠地绝肋。", "4HPyUF": "编辑: 锐骑", "4HR6tK": "# 腊日", "4HRazt": "[[慕容恪]]称[[慕容垂|吴王垂]][[将相]]之才十倍于己，以[[长幼]]之次故已得先之，愿[[陛下]]举国以听垂（101-134）。", "4HSAVP": "id: 雅_(概念)", "4HTUhb": "description: 汉武帝时谋臣，献推恩令削弱诸侯，又倡徙民实茂陵，权倾一时，后以诛杀燕王之事得罪，被族诛。", "4HTezO": "[099-088] 九月，秦丞相雄帅众二万还长安，遣平昌王菁略定上洛，置荆州于丰阳川，以[[步兵]]校尉金城郭敬为刺史。雄与清河王法、苻飞分讨孔持等。", "4HUaCa": "[[高肇]]以从妹妻[[茹皓]]，皓由是与肇益相昵狎（145-099）。[[魏主]]委任高肇，疏薄[[宗室]]，好桑门之法，不亲[[人事|政事]]（146-042）。高肇监造乐尺，然肇实不学，诏[[刘芳]]佐之（146-089）。高[[贵嫔]]有宠而妒，高肇势倾中外，[[魏主]][[皇后]]于氏暴疾而殂，人皆归咎高氏（146-106）。[[皇子]]昌卒，侍御师王显失于疗治，时人以为承高肇之意（147-008）。高肇数谮[[京兆]][[王愉]][[兄弟]]，愉不胜忿，杀[[长史]][[举兵]]反（147-013）。高肇及[[中尉]]王显素恶[[李平]]，奏免平名（147-022）。高肇为[[司徒]]，犹自以去家远，不乐（147-082）。又以[[大将军]]、平蜀[[大都督]]，将步骑十五万寇[[益州]]（147-110）。高肇以[[外戚]]进身，构害[[宗室]]，蠹政乱朝，其败也宜矣。", "4HUyVd": "tags: [西汉, 长安令]", "4HV5pp": "> 陆抗敕西陵诸军筑严围，自赤溪至故市，内以围阐，外以御晋兵。", "4HVV0h": "皇甫规以[[贤良]][[方正]]举，数上疏论羌事，其言明切。[[马贤]]将兵击羌，规上书言贤不恤军事，必败。未几贤果败没，人服其识（052-066、052-072）。及为[[泰山]][[太守]]，广设方略，寇虏悉平；复[[上疏]]请赴[[西凉]]讨羌（054-077）。在军中，[[大疫]]死者十三四，规亲入庵庐巡视[[将士]]，[[三军]]感悦（054-080）。规持节为将，多所举奏，又恶绝[[宦官]]，不与交通。于是中外并怨，乃共诬规货赂群羌，帝以规[[贤良]]策问本末，规力辩其诬（054-091）。[[张奂]]坐[[梁冀]]故吏[[免官]][[禁锢]]，诸交旧莫敢为言，独规前后七上荐举（054-104）。及[[党锢之祸]]起，规耻不得与，自上书言\"臣曾荐张奂，是附党也\"，朝廷知而不罪（055-056）。皇甫规以[[凉州]]豪杰之身，不阿[[权贵]]，不避[[党祸]]，在[[东汉]]中叶[[外戚]][[宦官]]交争之际，可谓特立独行之士。", "4HWOin": "**周几**，北魏将领。魏主遣左部尚书周几帅众镇鲁口以安集流民（117-033）。周几穷讨丁零翟猛雀馀党（117-085）。魏主使周几与奚斤、公孙表同入寇刘宋（119-080）。周几、娥清等南渡河（119-091）。周几、娥清徇地至湖陆、高平（119-118）。魏主命周几镇河南（119-128）。与娥清镇枋头（119-137）。周几寇许昌（119-140）。后率万人袭陕城，会周几卒于军中（120-094, 120-099）。", "4HWYn2": "[[韩昭侯]]以[[申不害]]为相，\"[[申不害]]者，郑之贱臣也，学黄老[[刑名]]以干昭侯，昭侯用为相，内修政教，外应[[诸侯]]\"（002-047），韩国大治。[[韩昭侯]]尝作高门，屈宜臼曰：\"君必不出此门。何也？不时。吾所谓时者，非时日也。夫人固有利、不利时。\"后果如其言（002-086）。[[韩昭侯]]任[[申不害]]，修术行道，国内以治，[[诸侯]]不来侵伐。", "4HWojr": "**贡院**，唐宋时期科举考试的专用场所。唐文宗时贡院奏进士复试诗赋。五代后汉时举人喧噪于贡院门，苏逢吉命执送侍卫司，欲痛棰而黥之，史德珫谏止。", "4HX1FN": "id: 棘", "4HX4ua": "**乾亨**，[[南汉]][[刘岩]][[年号]]，自[[丁丑]]年至乙酉年（公元917—925年），凡九年。乾亨元年，[[刘岩]]即[[皇帝]]位于[[番禺]]，[[国号]]大越（后改[[南汉]]），[[改元]]乾亨。", "4HXJQv": "| 称号 | 姓名 | 在位年数 | 与前代关系 |", "4HXKX9": "王敬则，晋陵南沙人。母为巫，敬则少时以屠狗为业，后为[[盗贼]]，入宋军以功补暨阳令。宋末从[[萧道成]]，以佐命功封[[寻阳]]郡公，官至[[大司马]]。永泰元年（498年），[[起兵]]反[[齐明帝]]，兵败被杀，时年六十四。子[[王元]]迁，嗣爵，与敬则同死。敬则出自寒微，起于盗屠，而登[[将相]]之位，在[[南北朝]][[士族]][[社会]]中尤为罕见。然[[起兵]]失败，举族[[覆灭]]，亦见[[寒门]]武将于权力斗争中之脆弱。", "4HXesN": "**殷鉴不远**，本出《诗经·大雅·荡》：\"殷鉴不远，在夏后之世。\"[[资治通鉴]]中多次引此语，借前代覆亡以警当世。[[东汉]]末，[[大将军]][[何进]]欲召[[董卓]]入京诛[[宦官]]，侍[[御史]]郑泰谏曰：", "4HXhkG": "[016-079] [[汉景帝|孝景皇帝]]下四年", "4HXzR8": "新增: 虏", "4HYIeP": "> 皇子嶷为豫章王，映为临川王，暠为安成王，锵为鄱阳王。", "4HYRYD": "### 作考课法", "4HZCJg": "[[田单]]在临淄为市掾，以铁笼傅车轊得免于难（004-071）。及田单破燕，迎[[齐襄王]]于莒，入临淄，封田单为安平君（004-072）。", "4HajZs": "本义为[[几案]]——\"案[[图籍]]\"（003-040），[[张仪]]说[[秦王]]案[[图籍]]以谋[[天下]]。\"案\"与\"按\"通：案地图即按图考察。", "4HcBul": "霍彦威的守城创造了五代防御战中的典型记录，\"刘知俊攻【霍彦威】于邠州，半岁不克，闻秦州降蜀，知俊妻子皆迁成都\"（269-054），以持久防御迫使刘知俊在半年围攻后无功而退，这一胜利奠定了他在后梁军事体系中的声誉。", "4HcNnR": "### [[第150卷]] 梁纪六", "4HdDDI": "| **纪年** | [[司马衍|晋成帝]][[咸康]]8年 |", "4HdlSR": "**华**，荣华。芬华为功名之饰，[[华山]]为[[地理]]之险，[[华阳|华阳君]]为秦之[[贵戚]]。", "4HeZgi": "[081-043] 十一月，壬寅，高平武公陈骞薨。", "4HekOl": "| 武十八年 | 马援缘海而进 | （043-065） |", "4HfpOa": "## 与王宗弼谋废立忧愤而卒", "4HgHhU": "新增: 修建", "4HgNOO": "[[战国]]七雄之一，经[[商鞅变法]]后迅速崛起，最终由[[秦始皇]]完成统一[[六国]]，建立[[中国]]历史上第一个中央集权帝国，共7位。", "4HgVY9": "> 以杜鸿渐为山南西道、剑南东、西川副元帅、剑南西川节度使，以平蜀乱。", "4Hgui1": "崔寔论政，言\"暴骨原野\"（064-030），以原野为战场之象。[[虞诩]][[谏官]]，\"足以陈原野\"（055-015），原野为陈尸之地。", "4Hh9YN": "济南，汉郡名。[[《资治通鉴》]]载[[吕后]]割齐济南郡为吕国，[[吴楚七国之乱|七国之乱]]济南王参与反叛。", "4HiA7y": "[[章邯]]渡河击赵，大破之。张耳与[[赵王歇]]走入巨鹿城，王离围之（008-040）。[[项羽]]既破秦军解巨鹿围，赵王歇及张耳得出（008-053）。", "4HiZYe": "[[寇恂]]还，遂与上谷长史景丹及[[耿弇]]将兵俱南，与渔阳军合（039-045）。景丹等纵突骑击之，宏等大败。秀曰：\"吾闻突骑天下精兵，今见其战，乐可言邪？\"（039-046）", "4HjkaF": "> （250-003）", "4Hjrwg": "吕諲领度支使：\"十二月，甲午，吕諲领度支使。\"（221-055）", "4Hk8V8": "秦末[[陈胜]]、[[吴广]]以戍卒赴[[渔阳]]，遇雨失期，遂举大泽之变（007-060）。[[汉文帝]]纳[[晁错]]言，募民徙塞下，以减戍卒之役（015-011、015-012）。汉与[[匈奴]][[和亲]]，诏减戍卒之半（013-031）。[[汉武]]时[[张骞]][[出使]]，募戍卒开辟[[西域]]（019-059）。", "4Hk8u1": "id: 长川", "4HkyJf": "[096-013] 赵王虎以燕王皝不会赵兵攻段辽而自专其利，欲伐之。[[司马迁|太史令]]赵揽谏曰：“岁星守燕分，师必无功。”虎怒，鞭之。皝闻之，严兵设备：罢六卿，纳言，常伯，冗骑常侍官。赵戎卒数十万，燕人震恐。皝谓内史高诩曰：“将若之何？”对曰：“赵兵虽强，然不足忧，但坚守以拒之，无能为也。”", "4HlTq7": "姑臧在十六国时期迭为[[凉州]]诸政权之都城，见证西北政局之兴替。前凉张寔被左右所杀，其党\"轘于姑臧市\"（091-045），姑臧作为政治中心之肃杀可见。刘曜攻凉州，扬言百道俱济直抵姑臧，张茂率众固守，大城姑臧修[[灵钧台]]以御敌（092-071）（092-074）。张骏继位后，晋愍帝使者史淑至姑臧，拜骏[[大将军]]、[[凉州牧]]、[[西平公]]（090-004），前凉以姑臧为中心维系晋室正朔，号召河西。张骏复徙陇西、[[南安]]民二千余家于姑臧，以实河西（093-078），姑臧作为区域中心的地位持续强化。自前凉经后凉、[[北凉]]，姑臧始终为河西政治文化之枢纽，其兴衰与[[十六国]]西北局势紧密相连。", "4Hls2h": "**白丁**，白丁，无官职之平民百姓，亦指未受教育之粗人。宋文帝谓江南白丁轻进易退（126-012）。王敬则军以白丁无器仗皆惊散（141-069）。勋官挽引劳苦与白丁无殊百姓不愿从军（201-045）。萧嵩选府兵及白丁十二万谓之长从宿卫（212-121）。诸州逃户准白丁例输当年租庸（213-031）。贺瑰发魏博白丁三万以供营栅之役（270-062）。吴琼胡装各帅白丁万人曳柴扬尘鼓噪助势（270-064）。", "4HmHuR": "tags: [东晋, 起义, 五斗米道]", "4HniYU": "id: 军事", "4HoDw1": "[257-017] 蔡将卢瑭屯于万胜，夹汴水而军，以绝汴州运路，硃全忠乘雾袭之，掩杀殆尽。于是蔡兵皆徙就张晊，屯于赤冈，全忠复就击之，杀二万馀人。蔡人大惧，或军中自相惊，全忠乃还大梁，养兵休士。", "4HoE5J": "> 平北将军樊毅都督清口上至荆山缘淮诸军，以备周。", "4HoUtm": "tags: [战国, 赵国, 秦国, 蔺相如, 外交]", "4HoW0i": "## 后尔朱荣时代", "4Hoqks": "| [[右将军安世]] | （024-004） | 夏，四月，癸来，帝崩于未央宫；无嗣。时武帝子独有广陵王胥，大将军光与群臣议所立， |", "4Hp1sm": "> 明宗圣德和武钦孝皇帝中之上长兴元年（庚寅，公元九三零年）", "4HpAJg": "> …，瓚辄称病不应；虞恐其终为乱，乃率所部兵合十万人以讨之。时瓚部曲放散在外，仓卒掘【东城】欲走，虞兵无部伍，不习战，又爱民庐舍，敕不听焚烧，戒军士曰：“无伤馀人，杀一伯珪…", "4HpX2L": "tags: [唐, 淮宁, 都虞候, 李希烈, 李勉, 德宗]", "4HqM7p": "周利用，[[唐中宗]]朝官员，历任[[大理正]]、[[御史中丞]]等职。先为五王（[[张柬之]]等）所恶，贬嘉[[州司马]]。[[武三思]]复起后，以周利用为右台[[侍御史]]，与[[桓彦范]]等素有嫌怨，[[武三思]]指使周利用持[[矫制]]赴岭外，逐一毒手[[诛杀]][[张柬之]]、[[桓彦范]]等被贬的[[功臣]]。史称[[御史中丞]]周利用、[[侍御史]][[冉祖雍]]、[[太仆丞]]李俊、光禄丞宋之逊、[[监察御史]][[姚绍之]]皆为[[武三思]][[耳目]]，时人谓之\"五狗\"，周利用居首。", "4HqYFU": "[[曹操]]举义兵以诛暴乱，大众已合，诸君何疑（059-076）。义兵既举，当全力以赴。", "4Hqotc": "廷尉在《[[资治通鉴概述|资治通鉴]]》中是[[秦汉]]司法体系的核心机构，廷尉的[[司法]]实践是[[法律]]独立于[[皇权]]的最重要屏障。[[李斯]]为[[廷尉]]时，以[[周]]文、武所封子弟同姓甚众然后属疏远相攻击如仇雠为由反对[[分封]]（007-033）——李斯以廷尉身份参与[[朝议]]，廷尉不仅是[[司法]]长官，也是[[国家]]大政的[[决策]]参与者。[[张释之]]为[[廷尉]]坚持依法判盗高庙玉环者为弃市而非族诛（014-017）——张释之的不畏[[皇权]]是[[汉代]]廷尉司法独立的最高典范，释之曰\"法者，天子所与天下公共也\"，廷尉的职责在于以法约束君主。[[汉文帝]]问[[陈平]]决狱之事，平曰\"陛下即问决狱责[[廷尉]]\"（013-077）——陈平以廷尉为司法专官为由回避[[丞相]]的司法责任，廷尉的专业化程度在此得到确认。[[吴公]]治平为天下第一召以为[[廷尉]]（013-081）——吴公以地方[[吏治]]第一升任廷尉，廷尉人选来自[[基层]]司法实践的经验积累。[[王恬开]]奏请族[[彭越]]（012-034）——廷尉在[[吕后]]操控下成为[[政治]][[迫害]]的工具。[[萧何]]为民请苑被下[[廷尉]]械系之（012-049）——廷尉在[[刘邦]]盛怒之下成为[[君主]]泄愤的刑具。廷尉在《通鉴》中的两重性——[[张释之]]的依法断案与王恬开的族诛之请——揭示了[[帝制]]中国[[司法]]的根本困境：廷尉的权威来自[[皇权]]，但其尊严却在于能否在一定范围内约束皇权。", "4Hr5rP": "- [[义]] | [[道]] | [[名实]] | [[子思]] | [[荀子]] | [[贾谊]]", "4HrOih": "[204-042] 十一月，辛酉，顗、绪伏诛，绍以太平公主故，杖一百，饿死于狱。", "4HrPdZ": "description: 鸾凤，鸾鸟与凤凰，祥瑞神鸟；喻贤才君子，枳棘非鸾凤所集喻小地不容大贤。", "4HswUt": "[175-028] 五月，戊午，隋封邗公雄为广平王，永康公弘为[[河间王]]。雄，[[汉高祖刘邦|高祖]]之族子也。", "4HtLnV": "> （058-005）", "4HuPoF": "description: 姓「嵇」的历史人物列表，共 2 人。", "4HvIBv": "- [[汉武帝]] — 轮台罪己诏的发布者", "4HvpVI": "description: 徇，巡行示众，也指为达到某种目的而牺牲（徇国、徇主）。", "4HwME1": "- 庾", "4HwP5t": "| 841 | 故杨嗣复出为湖南观察使 | （246-064） |", "4Hwign": "新增: 杞隐公", "4HwwH7": "前赵主[[刘曜]]与后赵主[[石勒]]长期对峙。刘曜东征洛阳，悬军千里。后赵将领程遐等谏阻石勒亲征，石勒不听，按剑叱退众人，决意亲救洛阳（094-047）。", "4HxT8E": "| [[冯跋]] | （114-090） | 初，[[中卫]][[龙骧将军|将军]][[冯跋]]及弟侍御郎素弗皆得罪於熙，熙欲杀之，跋[[兄弟]][[亡命]][[山泽]]。熙[[赋役]]繁数， |", "4HyEZs": "[[黄初]]年间，陈群主持制定了影响后世数百年的[[选官]][[制度]]：", "4HzQv3": "> 辛丑，魏上党王天穆及尔硃兆破邢杲于济南，杲降，送洛阳，斩之。兆，荣之从子也。", "4HzWtr": "[004-015] 秦楼缓免相，魏冉代之。", "4X03vC": "[020-035] 骞既至乌孙，昆莫见骞，礼节甚倨。骞谕指曰：“乌孙能东居故地，则汉遣公主为夫人，结为兄弟，共距[[匈奴]]，[[匈奴]]不足破也。”乌孙自以远汉，未知其大小；素服属[[匈奴]]日久，且又近之，其大臣皆畏[[匈奴]]，不欲移徙。骞留久之，不能得其要领，因分遣副使使大宛、康居、大月氏、大夏、安息、身毒、于阗及诸旁国，乌孙发译道送骞还，使数十人，马数十匹，随骞报谢，因令窥汉大小。是岁，骞还，到，拜为大行。后岁馀，骞所遣使通大夏之属者，皆颇与其人俱来，于是西域始通于汉矣。", "4X06n7": "仓场为收纳[[赋税]]、储存物资的官方场所。唐代仓场制度完善，设诸色仓场使、[[仓库]]官以掌之。[[黄巢之乱]]时，贼军遣人[[焚烧]]仓场，以震骇[[京师]]（241-010），可见仓场在战争中的战略价值。", "4X0LMc": "- [[太宗]] — 下令斩张君乂的皇帝", "4X0N6z": "[138-038] [[魏主]]使录尚书事广陵王羽持节安抚六镇，发其突骑。丁亥，魏主辞永固陵；己丑，发平城，南伐，步骑三十馀万；使太尉丕与广陵王羽留守平城，并加使持节。羽曰：“太尉宜专节度，臣正可为副。”魏主曰：“老者之智，少者之决，汝无辞也。”以河南王干为车骑大将军、都督关右诸军事，又以司空穆亮、安南将军卢渊、平南将军薛胤皆为干副，众合七万出子午谷。胤，辩之曾孙也。", "4X0Tbk": "| 291 | 郭彰、石崇、陆机、机弟云、和郁及荥阳潘岳、清河崔基、勃海欧阳建、兰陵缪征、… | （082-047） |", "4X0V8v": "> （192-091）", "4X0khZ": "编辑: 朝集", "4X0njD": "| [[宜都王铿]] | （139-058） | 鸾以吴兴太宗孔琇之行郢州事，欲使之杀晋熙王銶。琇之辞不许，遂不食而死。琇之，靖之 |", "4X1gGb": "| 平十五年 | 上以显亲侯窦固尝从其世父融在河西 | （045-066） |", "4X1hdW": "label: 阚璠", "4X21yW": "dynasty: 南朝·宋", "4X3pve": "[165-051] 柔然可汗庵罗辰叛齐，齐主自将出击，大破之，庵罗辰父子北走。太保安定王贺拔仁献马不甚骏，齐主怒，拔其发，免为庶人，输[[晋阳]]负炭。", "4X45g1": "| [[崔毖]] | （091-018） | 徐龛寇掠济、岱，破东莞。帝问将帅可以讨龛者于王导，导以为太子左卫率太山羊鉴，龛之 |", "4X4PVv": "| 416 | ”[[中军咨议参军]]张邵言于裕曰：“人生危脆 | （117-063） |", "4X4RoC": "[[汉高祖刘邦|汉高祖]][[刘邦]]，字季，父曰刘太公，母曰刘媪（007-098）。[[刘邦]]为[[布衣]]时，不事生产，及壮为[[泗水]][[亭长]]。娶[[吕后|吕雉]]为妻，生[[汉惠帝|刘盈]]及[[鲁元公主]]。[[秦末]][[起兵]]反秦，先入[[关中]]，与[[项羽]]争[[天下]]四年，终即[[皇帝]]位。立[[太子]]刘盈为嗣，尝欲废之立[[赵王]]如意，以[[张良]]、[[叔孙通]]之谏而止（012-048）。[[汉高祖刘邦|高祖]]崩，[[太子]][[即位]]为[[汉惠帝]]，[[吕后]][[临朝]][[称制]]（012-055）。", "4X5NAm": "徙都指古代政权将都城迁移至新的地点，通常出于政治、军事或经济发展需要。[[《资治通鉴》]]中[[战国|战国时期]]徙都之事频发。", "4X6j1n": "| 586 | 隋复令崔仲方发丁十五万 | （176-061） |", "4X6kmw": "编辑: 传国玺", "4X6oC0": "陈胜吴广起义时，义军假借公子[[扶苏]]与楚将项燕之名，以号召天下（007-084）。诸侯并起，秦朝迅速崩溃。后来贾谊总结秦朝灭亡，指出胡亥被赵高所教，所学皆为刑法酷吏之道，所以即位即见乱象（014-050）。", "4X7L9L": "> （104-103）", "4X7Pqi": "[[沮授]]为[[袁绍]]谋主，前后献策甚多：劝绍迎[[汉献帝|天子]]都[[鄄|鄄城]]，[[挟天子]]以令[[诸侯]]（061-053）；[[官渡]]战前谏绍宜[[务农]]息民、缓师持久（063-007）。", "4X85dV": "id: 白敏中", "4X8ERn": "# 司马楚之", "4X8cPd": "id: 项燕", "4X8muE": "| 534 | 多举元赞。 | （156-084） |", "4X8wmC": "刘裕参军击孙恩，独驱数千贼，崭露头角：", "4X97Qs": "苏绰，字令绰，京兆[[武功]]人。[[西魏]][[行台]]左丞，[[宇文泰]]谋主。创制立法，定[[文案]]朱出墨入之制。", "4X9KMK": "> [[【孙权】]]击山贼麻、保二屯，平之。", "4X9Mif": "[[吐蕃]][[大举]][[入寇]]，年末陷[[石堡城]]：", "4XABTF": "[[孙吴|吴起]]与[[士卒]]同[[衣食]]分劳苦（001-016）。[[子思]]论[[君臣]]同声贤之则善无从生（001-090）。[[商鞅]]令告奸与斩敌同赏（002-020）。[[公孙龙]]善为坚白[[同异]]之辩（003-089）。", "4XAShL": "> 乞伏国仁自称大都督、大将军、单于，领秦、河二州牧，改元建义。", "4XAq0Z": "[050-031] 孝安皇帝元初五年", "4XB0HI": "[187-035] 隋吏部侍郎杨恭仁，从宇文化及至河北；化及败，魏州总管元宝藏获之，己巳，送长安。上与之有旧，拜黄门侍郎，寻以为凉州总管。恭仁素习边事，晓羌、胡情伪，民夷悦服，自葱岭已东，并入朝贡。", "4XB4QV": "label: 崔群", "4XBOJm": "[[司马光]]记录司马懿的崛起，展示了[[曹魏]][[权力]]由曹氏向[[司马氏]]转移的历史进程。司马懿的深谋忍耐是其成功的关键，但其[[孙建]]立的晋朝随后陷入[[八王之乱]]，历史的讽刺意味令人深思。", "4XC4rA": "> 御史中丞崔器令百官受贼官爵者皆脱巾徒跣立于含元殿前。", "4XCAec": "及[[北齐]]诸州镇尽入于周，唯傅伏与[[营州]][[齐州刺史|刺史]][[高宝宁]]不下（173-023）。周主擒尉相贵，招傅伏，伏不从；齐人以伏为[[行台]][[右仆射]]。周主克[[晋阳|并州]]，复遣[[韦孝宽]]招之，令其子以上[[大将军]]、武乡公[[告身]]及金、马贻伏，伏不受（173-026）。及周主至[[晋阳]]，遣[[高阿那肱]]等百馀人临汾召伏，伏出军隔水相见，问：「[[天子]]今何在？」阿那肱曰：「已被捉矣。」伏仰天大哭，率众就泣，然后降。周主见之曰：「何不早降？」伏流涕曰：「臣三世为齐臣，食齐[[俸禄]]，不能自死，羞见[[天地]]。」周主执其手曰：「为臣当若此。」（173-028）傅伏以[[北齐]]末将，力尽而降，周主犹褒其忠，较之[[高阿那肱]]之辈卖主求荣者，其[[忠义]]不可同日而语。", "4XCC5y": "诸葛长民[[骄纵]]贪侈，惧[[刘裕]]按之。及[[刘毅]]被诛，长民益不自安。裕在[[江陵]]，[[辅国将军]]王诞白裕求先下，裕曰：\"诸葛长民似有自疑心，卿讵宜便去！\"诞曰：\"长民知我蒙公垂眄，今轻身单下，必当以为无虞，乃可少安其意耳。\"裕笑曰：\"卿勇过[[贲]]、[[夏育|育]]矣！\"乃听先还（116-054）。裕自[[江陵]]东还，骆驿遣[[辎重]][[兼行]]而下，前刻至日，每淹留不进。长民与[[公卿]]频日奉候于[[新亭]]，辄差其期。乙丑晦，裕轻舟径进，潜入东府。三月，丙寅朔旦，长民闻之，惊趋至门。裕伏[[壮士]]丁旿于幕中，引长民进语，遂杀之（116-064）。诸葛长民以从[[刘裕]][[起兵]]之功，[[位极人臣]]，然[[骄纵]]贪侈，暗怀异图，终为裕所诛。其死也，裕使王诞先归安其意，己则轻舟潜还、[[伏兵]]幕中，智算之深，长民岂能测哉！", "4XCnj5": "> （293-023）", "4XDFiD": "- [[李广]] — 张骞曾与李广同出右北平", "4XEis7": "> （066-017）", "4XFq6m": "enrich-quality: 新增「保据凉州」节", "4XGE8r": "label: 秦丰", "4XGZJD": "| **纪年** | [[唐高宗]]仪凤3年 |", "4XGojv": "| 618 | 其余将佐[[刘德威]]、[[贾闰甫]]、[[高季辅]]等 | （186-035） |", "4XH9T5": "description: 浇薄，人情淡薄，社会风气浮薄不淳。", "4XIpal": "新增: 严砺", "4XJIIb": "新增: 韦承庆", "4XJOZx": "朱温代唐建梁后，韦庄力排众议，劝王建称帝：", "4XJnWX": "周遣襄州[[总管]]卫公直督柱国[[陆通]]、[[大将军]]田弘、权景宣、元定等将兵助梁（170-023）。周[[总管]]田弘从梁主出顿纪南，[[昼夜]]拒战十旬（170-055）。周以柱国田弘为大[[司空]]（171-057）。田弘以[[战功]]官至大[[司空]]，为[[北周]]柱国重臣。", "4XJqhN": "id: 张瓘", "4XJwFm": "label: 蔡撙", "4XK3WT": "[[沮渠蒙逊]]卒，子[[沮渠牧犍]]立。[[北魏]][[拓跋焘]]伐凉，牧犍[[出降]]（123-082）。[[魏主]]徙[[沮渠牧犍]][[宗族]]及[[吏民]]三万户于[[平城]]，犹以妹婿待牧犍（123-085）。[[凉州]]自[[张轨]]以来号为多士，牧犍尤喜[[文学]]，以[[阚骃]]为[[姑臧]][[太守]]，[[刘昞]]、[[索敞]]为国师[[助教]]（123-086）。北凉既亡，[[河西]]诸国尽归[[北魏]]。", "4XKHeJ": "贤良，汉代[[察举]]取士科目，与方正合称\"贤良方正\"。[[《资治通鉴》]] 载举贤良之事。", "4XKPho": "[[秦昭王]]以十五城换[[和氏璧]]，赵惠文王以[[蔺相如]][[出使]]，终于[[完璧归赵]]（004-057）。随后在[[渑池之会|渑池会盟]]中，[[廉颇]]、[[蔺相如]]联手，使[[王镕|赵王]]免于[[秦国]]羞辱（004-070）。", "4XKPkT": "[207-034] 丙申，以相王知左、右羽林卫大将军事。", "4XKmHv": "[[韦宙]]（？—？），字为庆，[[宣宗|唐宣宗]]、[[懿宗]]朝官员。他以父[[韦丹]]在江西的[[惠政]]获[[宣宗]]特别信任；以[[度支]]副使身份巡抚[[边境]]禁止[[侵掠]]；[[平定]]洪州毛鹤叛乱；出任[[岭南]]东道[[节度使]]，主持南疆对[[南诏]]的防务，以加[[同平章事]]结束仕途。", "4XLjG0": "李抱真在德宗朝获得军政重任，\"以[[泽潞]][[行军]][[司马]]【李抱真】兼知磁、邢两州[[留后]]\"（225-079），在[[昭义]][[节度使]][[李承]]昭患病之际代理军政，继而正式出任[[节度使]]（226-028）。", "4XLmuG": "> 太子引兵去，驱四市人凡数万众，至长乐西阙下，逢丞相军，合战五日，死者数万人，血流入沟中。", "4XM6iu": "> 为其俎豆、管弦之间小不备，因是绝而不为，是去小不备而就大不备，惑莫甚焉！", "4XMdX7": "> 鄠初至安南，杀蛮酋杜守澄，其宗党遂诱道群蛮陷交趾，朝廷以杜氏强盛，务在姑息，冀收其力用，乃赠守澄父存诚金紫光禄大夫。", "4XMeWf": "id: 交趾太守", "4XMg1p": "新增: 尹昭", "4XMvww": "| [[决大计]] | （025-026） | 会李竟坐与诸侯王交通，辞语及霍氏，有诏：“云、山不宜宿卫，免就第。”山阳太守张敞 |", "4XNQoe": "| 583 | 幽州总管阴寿帅步骑十万出卢龙塞 | （175-107） |", "4XNRV2": "[[汉宣帝]]时奏《盛德》、《文始》、《五行》之舞（024-046），以五行命名[[乐舞]]。[[刘向]]集合上古至秦汉[[灾异]]之记，著《洪范五行传论》（030-059）。[[刘歆]]继之，以五行推演[[历数]]。[[王莽]]引[[五行志]]言柏梁灾为巫蛊之应（073-012）。五行学说在汉代为官方主流[[宇宙观]]，与[[阴阳]]、[[灾异]]、[[符瑞]]等观念紧密相连。", "4XNSxC": "[[崔浩]]（381—450年），字伯渊，[[清河]]东武城人，[[北魏]]最重要的政治[[谋士]]，善[[天文]]、[[术数]]、[[谋略]]，多次以精准的预判左右国家大政。他辅佐道[[武帝]]、明[[元帝]]、太[[武帝]][[三代]]，参与[[北魏]]统一北方的诸多战役，晚年因主编[[北魏]][[国史]]、直书皇室隐私而遭[[族诛]]，是[[中国]]历史上文人因修史而死的著名案例。", "4XNiT5": "description: 汉代十三刺史部之一，辖境相当于今甘肃、宁夏一带，河西走廊之要冲。", "4XOOhy": "[[刘渊]]（？—310年），字元海，新兴[[匈奴]]贵族，[[匈奴]]左贤王后裔，自称[[西汉|汉朝]]后裔（[[汉高祖刘邦|刘邦]]之甥后代），以此建国号\"汉\"，史称[[前赵]]或汉赵。他博通经史、礼贤下士，趁[[八王之乱]]起兵，建立十六国时期第一个[[胡人]]政权，开创了[[五胡]]乱华的历史序幕。", "4XPEuo": "## 晋唐", "4XPbtY": "- [[苻洪]] — 麻秋劝其取关中后为其所杀", "4XPjuL": "| 617 | [[晋阳]]令[[武功]]刘文静 | （183-060） |", "4XQ492": "[250-108] 春，二月，归义节度使张义潮奏北庭回鹘固俊克[[西州]]、北庭、轮台、清镇等城。", "4XRbjl": "[164-039] 戊午，景遣卫尉卿彭隽等帅兵入殿，废帝为晋安王，幽于永福省，悉撤内外侍卫，使突骑左右守之，墙垣悉布枳棘。庚申，下诏迎豫章王栋。栋时幽拘，廪饩甚薄，仰蔬茹为食。方与妃张氏鉏葵，法驾奄至，栋惊，不知所为，泣而升辇。", "4XSE8C": "| 389 | 乞伏乾归击侯年部 | （107-077） |", "4XSJi1": "新增: 永淳", "4XSg96": "description: 手掌", "4XT1l3": "## 谋诛宦官被杀", "4XU2df": "公元871年，[[唐懿宗]][[咸通]]11年。", "4XUUa8": "| [[尔硃兆]] | （153-029） | [[中军]][[大都督]]兼[[中领军|领军]][[大将军]][[杨津]]入宿[[殿中]]，扫洒宫庭，封闭[[府库]]，出迎[[魏主]]于北邙，流涕[[谢罪]] |", "4XUpvj": "赵[[将军]][[王擢]]击张重华，袭[[武街]]，执[[护军]]曹权、胡宣，徙七千馀户于[[雍州]]（097-084）。张重华将宋秦等帅户二万降于赵。重华以[[谢艾]]为[[使持节]]、[[军师]][[将军]]，帅步骑三万进军临河（097-098）。张重华使[[将军]]牛旋御之，退守[[枹罕]]，[[姑臧]]大震（097-099）。", "4XUqlw": "> （006-059）", "4XVZbr": "[[曹操]]诣[[扬州]][[募兵]]，与司马沛国夏侯惇等得千余人，还屯河内（059-076）。夏侯惇是[[曹操]]最早的军事合作者之一，也是最亲近的[[宗族]]力量。", "4XVniA": "## 不臣之责", "4XWG0k": "description: 隋大业年间，杜伏威与辅公祏在江淮地区聚众起义，转战江淮，据有历阳、丹杨等地，后降唐，是隋末南方最重要的反隋势力之一。", "4XWmWF": "> 跋等与左卫将军张兴及苻进馀党作乱。跋素与慕容云善，乃推云为主。", "4XWtcy": "**奔命**原指紧急[[调发]]的军队，后引申为奔赴急难、疲于应付，为古代[[军事]]中快速反应和调动的重要[[概念]]。", "4XXa8y": "### 议御诸葛亮", "4XXrrS": "咨议[[参军]]梅陶说[[王敦]]曰：\"[[周访]]与侃亲姻，如[[左右]]手，安有断人左手而右手不应者乎！\"敦意乃解（089-051）。[[陶侃]]薨，[[尚书]]梅陶与亲人曹识书曰：\"陶公机神明鉴似魏武，忠顺勤劳似[[诸葛亮|孔明]]，[[陆抗]]诸人不能及也。\"（095-052）。", "4XZGOm": "周访，字士达，庐江寻阳人。东晋名将，平定江州杜苾之乱。", "4XZu5j": "孔戣（751-824年），字君严，[[冀州]]人，[[唐代]]大臣。宪宗时为[[国子祭酒]]、[[华州刺史]]，奏罢[[明州]][[岁贡]]蚶、蛤、淡菜，以省水陆递夫劳费（240-027）。穆宗时[[岭南节度使]]，桂管[[观察使]][[裴行立]]、容管[[经略使]][[阳旻]]请讨黄洞蛮，孔戣屡谏以为不可，言\"此[[禽兽]]耳，但可自计[[利害]]，不足与论[[是非]]\"，帝不从，大发江、湖兵会讨（241-031）。", "4XbNSi": "> 始，臣起下邳，与上会留。", "4XcT0N": "tags: [政治, 经济, 军事, 制度]", "4Xco6a": "| **纪年** | [[唐哀帝]][[天祐]]元年 |", "4Xe3S4": "label: 逃归", "4XeHKv": "[166-104] 甲申，魏葬安定文公。丁亥，以岐阳之地封世子觉为周公。", "4XeOBz": "> 当今之计，若举冀州以让袁氏，彼必厚德将军，瓚亦不能与之争矣。是将军有让贤之名，而身安于泰山也。", "4XfBZb": "[[隋文帝]]统一币制，更铸[[五铢钱]]，背面好肉皆有周郭，每一千重四斤二两，悉禁古钱及私钱，置样于关，不如样者没官销毁之，自是[[钱币]]始壹，民间便之（175-036）。此为[[中国]]币制统一之重要里程碑。古钱之流通与禁止，实为[[中国]]古代[[货币]]史的长期难题，从汉[[五铢]]到唐开元通宝，历代新钱出而古钱未废，至隋唐大一统始得解决。", "4XfBfm": "description: 公元438年，宋文帝元嘉15年。无大事记载。", "4Xg17L": "新建爵位: 昌成君", "4XgTWL": "编辑: 传舍", "4XgYF7": "| **[[资治通鉴概述|通鉴]]卷目** | [[第136卷]] · 南北朝纪 |", "4XgYFr": "| 633 | ”魏征欲上偃武修文 | （194-031） |", "4Xh5DN": "description: 北魏五原戍城，后燕平城方向要塞", "4XhuvX": "**关内侯**，秦汉二十等爵第十九级，有侯号而无国邑，居京畿[[关内]]。", "4Xi5rR": "- [[荀彧]] | [[魏明帝]]", "4Xi6FM": "description: 成德节度使，杀李惟岳自立", "4XiSUP": "description: 大将军从事中郎，古代官职。", "4XiUEb": "[101-039] 孝宗穆[[皇帝]]下隆和元年（壬戌，公元三六二年）", "4XiXPb": "| 588 | 护军将军樊毅言于仆射袁宪曰：“京口、采石俱是要地 | （176-131） |", "4Xiee4": "concept_cat: 成语", "4Xiooi": "id: 齐王司马冏", "4Xjcdf": "[[高德政]]为[[高澄]]所用，使佐[[高洋]]留守于邺（160-031）。及[[高洋]]为[[齐王]]，[[德政]]为管记，由是亲昵，言无不尽（163-032）。[[德政]]录在邺诸事，条进于洋，参预[[北齐]]禅代之谋（163-033）。", "4XkJ8x": "[[后晋]][[迁都]]，建东京[[开封]]府：", "4Xl8Za": "编辑: 胶西王", "4XlOf9": "## 平定岭南余乱", "4XlSZm": "> （023-011）", "4XlpT4": "description: 帝王陵墓旁的寝庙建筑。", "4Xlu5Z": "**刘遐**，[[东晋]]临淮[[魏郡太守|太守]]。[[左丞相|丞相]]睿以刘遐为[[平原]][[内史]]（089-097）。以[[下邳]][[内史]]刘遐领鼓城[[内史]]，与[[徐州刺史]]蔡豹等共讨周抚（090-066）。刘遐、[[徐龛]]击周抚于寒山，破斩之（091-003）。及[[论功]]，刘遐先之，[[徐龛]]怒，以[[泰山]][[叛降]][[石勒]]（091-007）。后以临淮[[魏郡太守|太守]]刘遐、[[鲜卑]]段[[文鸯]]等讨[[徐龛]]（091-018）。", "4Xm0JO": "> 美鬓长大则贤，射御足力则贤，伎艺毕给则贤，巧文辩慧则贤，强毅果敢则贤，如是而甚不仁。夫以其五贤陵人，而以不仁行之，其谁能待之？", "4XnFI6": "id: 斩马剑", "4Xnmlr": "新增: 十室九空", "4XnrMv": "[012-012] 十二月，上行如[[洛阳]]。", "4XoRNb": "tags: [政治, 建筑]", "4Xp0b6": "| 944 | 前威胜节度使何重建守杨刘镇 | （284-003） |", "4XqLOy": "| [[将军李安民]] | （135-023） | 丁酉，以[[太子詹事]][[张绪]]为[[内史令|中书令]]，[[齐国]][[左卫将军]][[陈显达]]为[[中护军]]，[[右卫将军]][[李安民]]为中领军 |", "4XrJU4": "> （180-029）", "4XrNXR": "> 仇液之韩，王贲之楚，富丁之魏，赵爵之齐。", "4Xs5ku": "崔植在[[唐宪宗]]朝为[[给事中]]时，曾封还[[敕书]]极论减[[官俸]]之非（240-078），时人许其刚直。然及[[唐穆宗]][[即位]]，崔植入相为[[中书侍郎]]、[[平章事|同平章事]]（241-061），居相位而不能匡正君失——穆宗酣宴不留意[[天下]]之务，崔植与[[杜元颖]]全无远略，不知[[安危]][[大体]]（241-095）。[[幽州]]、[[成德]]二镇再叛，崔植等苟崇重[[张弘靖]]、惟割瀛莫二州以授之，[[处置]]失宜（241-095），致[[河朔]]再乱不可收拾。史家评崔植与[[杜元颖]]、[[王播]]为相，\"皆庸才，无远略\"（242-046）。崔植之失，不在[[奸邪]]，而在平庸——值穆宗嬉游无度之时，不能[[犯颜]][[直谏]]；当[[河朔]]桀骜不驯之际，不能[[制胜]]谋远。[[长庆]][[河北]]再叛，实与崔植等庸相误国密切相关。罢相后为[[刑部尚书]]（242-049），终究不能挽回长庆间[[藩镇]]复叛之大局。", "4XsRNi": "id: 前9年", "4XtQVl": "深井里聂政（001-037）。深结韩之亲（002-065）。秦虽欲深入则狼顾（002-094）。深怨结于齐（004-047）。", "4Xtd1F": "| 947 | ”以[[左右]]卫圣[[统军]]、[[忠武节度使]]、[[平章事|同平章事]]李金全为[[北面行营招讨使]] | （287-031） |", "4XtniQ": "新建年份条目：前349年", "4XtoLj": "label: 刘长", "4Xuemm": "丁奉: 新增「吴末栋梁」章节", "4XvCj9": "[[蝮蛇]]为剧毒蛇类，多见于[[南方]][[山林]]。[[淮南王]][[刘安]][[谋反]]，[[伍被]]谏曰：[[南方]]\"林中多[[蝮蛇]]、猛兽，夏月暑时，欧泄霍乱之病相随属\"（017-060）。又曰\"[[南方]]暑湿，近夏瘅热，暴露水居，[[蝮蛇]]蠚生\"（017-061），以[[南方]]险恶劝阻[[出兵]]。", "4XvJBP": "id: 石崇", "4XwK4V": "# 硃姓", "4XwXdZ": "[006-059] 春，蒙骜伐魏，取旸、有诡。三月，军罢。", "4XwXod": "## 为尚书左丞", "4XwpCM": "label: 慕容云", "4XxBRo": "[[汉高祖刘邦]]即[[皇帝]]位于[[汜水]]之阳，更王后曰皇后，[[太子]]曰皇[[太子]]（011-012）。[[汉惠帝]][[即位]]后，尊皇后曰[[皇太后]]（012-055）。", "4XxlDZ": "堂，正厅。文侯亲下堂迎任座以为上客（001-015）。宋王为长夜之饮，堂上堂下皆呼万岁（004-041）。堂为建筑之正室，朝堂为君臣议事之所。堂堂正正、堂而皇之皆取正大之意。", "4XyAoh": "| 514 | 假太子右卫率康绚都督淮上诸军事 | （147-111） |", "4XyUo2": "新建词条：李敏", "4XyegR": "| 958 | 唐太弟景遂前后凡十表辞位 | （294-018） |", "4Xz1ya": "label: 辟召", "4XzVFl": "新建年份条目：公元862年", "4Xzqbg": "## 权知凤翔", "4b09tZ": "> 中郎东方朔陛戟殿下，辟戟而前曰：董偃有斩罪三，安得入乎！", "4b0URa": "由两马并驾引申为并列、对偶。[[诸葛亮]]使[[廖立]]垂泣、[[李平|李严]]致死，[[管仲]]夺伯氏骈邑三百（072-068），骈邑即相连之邑。[[晋]][[王衍]]以\"骈俪\"论文（080-055），骈俪即对偶之文。[[唐]]中期[[科举]]以[[骈文]]取士，[[李商隐]]工四六骈体，号\"三十六体\"（250-091），骈文盛行于唐代公文[[奏议]]。[[唐武宗]]时[[李德裕]]执政，曾奏请罢骈体用古文（250-105），可见骈文在官场之地位。", "4b0g4P": "label: 幕客", "4b1Vqg": "> （214-057）", "4b224t": "[080-069] 兗、豫、徐、青、荆、益、梁七州大水。", "4b24YO": "> 襄阳太守宗岱承冏檄斩孙旂，永饶冶令空桐机斩孟观，皆传首洛阳，夷三族。", "4b2Ko0": "大城名都民人散亡，户口可得而数裁什[[二三]]（021-071）。", "4b2Thp": "**绯衣**，唐代四品、五品官员所服深绯色官袍，为品色服制度之一。", "4b3waw": "label: 比部", "4b4AvW": "label: 安成王顼", "4b4P0e": "description: 曹操之子，曹魏开国皇帝，逼迫汉献帝禅让，正式终结东汉，建立魏国，在位期间延续曹操奠定的基业，同时也是著名的文学家和诗人。", "4b5cXq": "**应詹**（？—333年），字思远，[[东晋]][[南平太守]]。", "4b78L8": "## 铁器官营与民间需求", "4b7ASR": "| 918 | 吴以前舒州刺史陈璋为东南面应援招讨使 | （270-043） |", "4b7XvC": "> 仁轨喜曰：\"天将富贵此翁矣！\"于州司请《唐历》及庙讳以行，曰：\"吾欲扫平东夷，颁大唐正朔于海表！\"", "4b8hBu": "## 谏议与改制", "4b9FlF": "**罪**，罪行、罪过。起恐得罪闻[[魏文侯]]贤乃往归之（001-016）。[[申不害|申子]]辟舍[[请罪]]（002-047）。伪得罪于燕而奔齐，[[苏秦]]之谋（002-120）。招致[[诸侯]]游士及有罪亡人，[[孟尝君]]养士（002-129）。杀一无罪而得[[天下]]仁者不为（004-049）。肉袒负荆至门[[谢罪]]，[[廉颇]][[蔺相如]][[将相和]]（004-070）。", "4b9Vn8": "**韦黯**，梁太府卿。侯景自寿阳南下，马头戍主刘神茂素为监州事韦黯所不容，乃献策于景，劝其往投寿阳（161-006）。及侯景围台城，朝廷命太府卿韦黯屯六门，缮修宫城，为受敌之备（161-037）。后韦黯与右卫将军柳津等分守宫城诸门及朝堂（161-038）。", "4b9uE8": "- [[曹魏]]", "4bB40I": "id: 公元422年", "4bBPLb": "提升四维质量档位 basic→standard", "4bBgyZ": "萧俛以监察职责坚持正义，\"中丞【萧俛】[[劾奏]]其状，[[裴度]]、[[崔群]]亦以为言。上曰：'姑与卿论[[用兵]]事，此小事朕自处之'\"（240-080），与[[裴度]]、[[崔群]]联名[[弹劾]]五坊使杨朝汶横征乱捕、迫取息钱的暴行。", "4bCoJZ": "新增: 众", "4bE5db": "> 虎贲中郎将梁松来候之，独拜床下，援不答。", "4bEGbh": "- [[王昭君]]（王嫱）— 和亲主角", "4bEN0H": "新增: 剑履", "4bERmy": "魏葬宣武[[皇帝]]于景陵。[[魏主]]及[[太后]]谒景陵。葬[[唐宪宗]]于景陵。", "4bFMgw": "- 相关概念：[[内忧外患]]", "4bFjZB": "[[高平陵之变]]后，[[曹爽]]被诛，[[司马懿]]召夏侯玄赴[[京师]]，以[[郭淮]]代其职（075-051）。夏侯玄\"有[[天下]]重名\"，[[司马师]][[秉政]]后令其任[[太常]]，郁郁不得志（076-029）。", "4bFw86": "> （237-036）", "4bGGh1": "description: 姓「念」的历史人物列表，共 1 人。", "4bHjc0": "东魏丞相[[高欢]]筑长城于肆州北山，西自马陵，东至土墱，四十日罢（158-125）。", "4bHx8O": "> 剑南节度使【鲜于仲通】讨南诏蛮，大败于泸南。时仲通将兵八万，分二道出戎、巂州，至曲州、靖州。", "4bIq7K": "张仪游[[诸侯]]无所遇，困于[[楚国]]，[[苏秦]]暗中召来羞辱，激其入秦——此实为[[苏秦]]的算计，以张仪牵制[[秦国]]、间接保护[[合纵连横|合纵]]（002-091-092）。", "4bJWcy": "**训**指训诫、[[教导]]，在《[[资治通鉴概述|资治通鉴]]》中用于[[君臣]]教诲与家庭教育。", "4bJXn4": "[[后秦]][[天水]]公延以[[枹罕]]之众攻[[临洮]]、武始、河关，皆克之（109-007）。", "4bJcZQ": "戴胄以[[忠义]]立场进谏，\"外兵曹军【戴胄】言于世充曰：'君臣犹父子也，休戚同之，明公莫若竭忠徇国，则家国俱安矣'\"（187-040），即便在主公[[虎牢]]关危急之际，仍以忠节劝诫，展现出不变的政治立场。", "4bKOtx": "id: 张文表", "4bKcjA": "> 以高万兴为保塞节度使，以绛州刺史牛存节为保大节度使。", "4bL7dD": "[086-018] 平昌公模遣将军宋胄趣河桥。", "4bLnST": "> 及楚王戊来朝，错因言：「戊往年为薄太后服，私奸服舍，请诛之。」诏赦，削东海郡。", "4bM8Fe": "配享，功臣从祀于[[帝王]][[宗庙]]，或[[皇后]]与[[皇帝]]同享[[祭祀]]之礼。燕主垂欲以兰后配享太祖（106-076）。[[明堂]]、[[太庙]]配祭配享（137-055）。二后配享，君臣并筵，嫂叔同室，窃谓不可（153-007）。", "4bMSAu": "[[司马光]]通过马超，展示了汉末乱世边地豪强的兴衰：以西凉强兵立威，以猛将之勇令[[曹操]]生畏，却因政治上的短视和军事上的孤立而覆亡，最终只能以归顺[[蜀汉]]为归宿，是那个时代英雄无路的典型写照。", "4bMWpJ": "label: 血战", "4bMkpO": "| [[将军陈显达]] | （138-003） | 春，正月，以[[骠骑大将军]][[王敬则]]为[[司空]]，镇军[[大将军]][[陈显达]]为江州刺史。显达自以门寒位重 |", "4bN4PL": "[[隋炀帝]]诏于[[汾州]]之北汾水之源营汾阳宫。[[樊子盖]]发[[关中]]兵击绛贼，自汾水之北[[村坞]]尽焚之。", "4bNWYu": "棺为[[丧礼]]之要器，厚薄有度，见[[仁政]]与[[廉]]俭。[[汉高祖]]令官给军士棺敛（010-039），为恤死之仁。[[文帝]][[遗诏]][[薄葬]]省礼（015-070），为[[节用]]之倡。[[张汤]]有棺无椁（020-027），见其廉而受冤。[[董贤]]发棺验尸（035-028），见[[王莽]]之酷。[[云敞]]冒死棺敛[[吴章]]（036-005），为[[节义]]之彰。[[通鉴]]记棺，见[[生死]]之际与[[礼制]]之维。", "4bO9Kl": "| 633 | 上皇命[[突厥]][[颉利可汗]]起舞 | （194-041） |", "4bOF5Q": "## 吕后崩，诸吕欲乱", "4bP4jx": "| [[河西臧希让]] | （222-058） | 甲午，奴剌寇[[梁州]]，[[鄂岳观察使|观察使]][[李勉]]弃城走，以邠州剌史[[河西]]臧希让为山南西道节度使。丙申， |", "4bPHqd": "> 蛮、夷即相帅为仁寿筑城，立廨舍，旬日而就。", "4bPUDE": "tags: [汉, 唐, 服饰]", "4bQfKO": "# [[幽州节度使]]", "4bQhBa": "| 563 | 大司马豆卢宁升阶 | （169-014） |", "4bQmFj": "> 荀悦论曰：荣辱者，赏罚之精华也。故礼教荣辱以加君子，化其情也。", "4bQwIH": "元天穆，[[北魏]][[宗室]]，太武帝五世孙。与[[尔朱荣]]善，荣兄事之，参与[[尔朱荣]]入洛及[[河阴之变]]，官至[[太尉]]、[[上党]]王。", "4bR4XY": "[[毛宝]]烧[[苏峻]]句容、湖孰[[积聚]]，峻军乏食。", "4bRAe2": "> （288-079）", "4bRGyT": "耿纯为[[东汉]]开国功臣，以率先率族归附[[刘秀]]、劝进称帝、诛除刘扬等功勋著称。其\"攀龙鳞，附凤翼\"之语，为后世形容从龙功臣的经典表述。耿纯所率宗族宾客自随，举族投效，其忠勇与决断，比于[[刘植]]、[[邳肜]]等，同为河北豪杰归附[[刘秀]]的代表人物。", "4bRTjQ": "| [[马长史王亮]] | （145-008） | 己酉，以[[大司马]][[长史]]王亮为中书监，兼[[尚书令]]。 |", "4bS4jd": "label: 谄谀", "4bTaRb": "仪结陈而去，入谷然后发丧（072-062）。庆之收步骑数千，结陈东还（153-028）。[[羊侃]]结陈徐还（160-052）。", "4bTbzm": "王郎在邯郸称帝后，河北郡国望风而降，形势对刘秀极为不利。信都是极少数未曾降附王郎的郡县：", "4bTlqn": "# [[右金吾卫将军]]", "4bTnIV": "description: 中国第一大淡水湖，位于江西北部，长江中游南岸，是长江的重要调蓄湖泊和水运枢纽。", "4bUb4d": "label: 司马欣", "4bVvov": "**灾咎**，古代指灾难祸患，常与[[天象]]人事相关联。[[汉桓帝]]时[[赵瑜]]言灾咎之征，执政者欲令依违其辞（055-029）。[[北魏明元帝]]问今[[四海]]分裂，灾咎之应在何国，[[崔浩]]以[[灾异]]之兴皆人事召之对（118-086）。", "4bVyCp": "> 遣车骑将军卫青出上谷，骑将军公孙敖出代，轻车将军公孙贺出云中，骁骑将军李广出雁门，各万骑，击胡关市下。", "4bWJnB": "| [[汉明帝|明帝]] | 刘彧 | 7年（465—472） | [[隋文帝|文帝]]第十一子 | [[泰始]]·泰豫 |", "4bWeaU": "周浚，字开林，[[汝南]]人，[[西晋]][[扬州]][[刺史]]，从伐吴。", "4bWnhK": "[249-018] 以[[兵部侍郎]]裴休为盐铁转运使。休，肃之子也。自太和以来，岁运江、淮米不过四十万斛，吏卒侵盗、沉没，舟达渭仓者什不三四，大堕刘晏之法。休穷究其弊，立漕法十条，岁运米至渭仓者百二十万斛。", "4bXZL4": "| 546 | 要须济江缚取萧衍老公、以为[[太平]][[寺主]]。 | （159-046） |", "4bXgko": "description: 古代云梦泽，楚地大泽，秦汉帝王游猎之所。秦始皇行至云梦望祀虞舜，汉高祖伪游云梦擒韩信，唐末犹有战事于云梦泽中。", "4bXz6u": "> 秦令下三十日不烧，黥为城旦；所不去者，医药、卜筮、种树之书。", "4bYgLe": "| [[恩侯许嘉]] | （029-005） | 夏，四月，癸未，平昌考侯王按薨。秋，七月，壬戌，以平恩侯许嘉为大司马、车骑将军。 |", "4bYvfO": "description: 三国末期魏国淮南地区接连发生的三次叛乱，分别为王凌之叛（251年）、毌丘俭文钦之叛（255年）和诸葛诞之叛（257-258年），皆以寿春为中心，均被司马氏平定。", "4bZYzc": "> 陆浑民孙狼等作乱，杀县主簿，南附[[关羽]]。羽授狼印，给兵，还为寇贼，自许以南，往往遥应羽，羽威震华夏。[[魏王]]操议徙[[许都]]以避其锐，丞相军司马[[司马懿]]、西曹属蒋济言于操曰：“于禁等为水所没，非战攻之失，于国家大计未足有损。[[刘备]]、[[孙权]]，外亲内疏，[[关羽]]得志，权必不愿也。可遣人劝权蹑其后，许割江南以封权，则樊围自解。”操从之。", "4bZxnZ": "- [[瀚海都护]] | [[燕然都护]] | [[安西都护]] | [[北庭都护]] | [[都护府]]", "4ba53j": "[134-060] 攸之有素书十数行，常韬在裲裆角，云是明帝与己约誓。攸之将举兵，其妾崔氏谏曰：“官年已老，那不为百口计！”攸之指裲裆角示之，且称太后使至，赐攸之烛，割之，得太后手令云：“社稷之事，一以委公。”于是勒兵移檄，遣使邀张敬儿及豫州刺史刘怀珍、梁州刺史梓潼范柏年、司州刺史姚道和、湘州行事庾佩玉、巴陵内史王文和同举兵。敬儿、怀珍、文和并斩其使，驰表以闻；文和寻弃州奔夏口。柏年、道和、佩玉皆怀两端。道和，后秦[[汉高祖刘邦|高祖]]之孙也。", "4baM3i": "姓氏页迁移: 郅（姓氏）", "4baN0p": "温璋与[[刘瞻]]共同力谏于上前（252-022）：", "4baa7R": "> 王澄过诣敦，自以名声素出敦右，犹以旧意侮敦。敦怒，诬其与杜苾通信，遣壮士扼杀之。王机闻澄死，惧祸，以其父毅、兄矩皆尝为广州刺史，就敦求广州，敦不许。会广州将温邵等叛刺史郭讷，迎机为刺史，机遂将奴客门生千馀人入广州。讷遣兵拒之，将士皆机父兄时部曲，不战迎降，讷乃避位，以州授之。", "4bacVP": "> 时内自关中，西暨蜀、汉，南尽江、淮、闽、越，北至[[晋阳|太原]]，所在出兵，而李正己遣兵扼徐州甬桥、涡口，梁崇义阻兵襄阳，运路皆绝，人心震恐。江、淮进奉船千馀艘，泊涡口不敢进。上以和州刺史张万福为濠州刺史。万福驰至涡口，立马岸上，发进奉船，淄青将士停岸睥睨不敢动。辛丑，汾阳忠武王[[郭子仪]]薨。子仪为上将，拥强兵，程元振、鱼朝恩谗谤百端；诏书一纸征之，无不即日就道，由是谗谤不行。", "4bap1l": "| **纪年** | 梁武帝中大通5年 |", "4bc2Hj": "> 帝自是无所忌惮，益得自恣，日夜与近习于后堂鼓叫戏马。常以五更就寝，至晡乃起。", "4bedIr": "**蚕**，吐丝织茧之虫，也喻逐渐侵蚀（蚕食）。", "4bedk9": "tags: [战国, 秦汉, 思想, 法家]", "4bepiB": "# 陈留", "4bf1aq": "[[司马光]]通过李克用的记录，展示了[[唐末]][[藩镇]][[割据]]如何演变为[[五代]]政权的历史进程。李克用以[[沙陀]]武力成为乱世[[枭雄]]，其子[[孙建]]立的[[后唐]]，成为[[五代]]中唯一以汉化胡族为主体的政权。", "4bfRRN": "id: 公元774年", "4bfm6q": "李子通被来整所破，奔海陵，收兵二万人（182-094）。李子通据海陵（183-013）。海陵贼帅臧君相帅众五万来争（186-037）。杜伏威据历阳，陈稜据江都，李子通据海陵（187-091）。唐以海陵刺王元吉追封巢王（196-036）。徐敬业至海陵界，阻风，其将王那相斩敬业来降（203-095）。", "4bfnOo": "创建河流/区域地名词条", "4bfxan": "- [[中元]]二年·[[汉明帝|明帝]][[即位]]", "4bgCfE": "李洪雅被囚（165-007）：", "4bgJp6": "> （151-026）", "4bh8HD": "蒯恩从[[刘裕]]追[[卢循]]，与[[王仲德]]等帅众追循（115-075）。又为龙骧将军，与[[王镇恶]]将百舸前发伐[[荆州]]（116-042）。至豫章口，蒯恩军居前，入[[江陵]]城（116-043）。又从[[刘裕]]伐蜀（116-056）。后[[刘裕]]召[[庐陵王义真|刘义真]]东归，使蒯恩如长安（118-080）。夏兵大至，蒯恩断后，力战连日，至青泥被禽（118-081）。蒯恩每战必为前锋，勇冠诸军，然卒以断后被俘，良可惜也。", "4bhFGX": "**组**，丝带。[[子婴]]素车白马系颈以组，封[[皇帝]]玺[[符节]]以降（009-003）。[[锦绣]]纂组害[[女工]]者也（016-112）。方寸之印丈二之组填抚方外（017-062）。[[杨仆]]怀银黄垂三组夸乡里（020-077）。[[霍光]]解汉帝玺组奉太后（024-020）。", "4bhW4C": "> 辛未，东路军破贼将孙马骑于上疁村，贼将王皋惧，请降。", "4bi0VG": "> 六月，壬子，以左骁卫大将军裴思说充[[灵武]]军大总管，以备突厥。", "4biSgA": "| [[已落其手]] | （288-006） | [[侯益]]盛毁[[王景崇]]于朝，言其恣横。景崇闻益尹[[开封]]，知事已变，内不自安，且怨[[朝廷]]。会诏 |", "4bit6J": "# 孙恩卢循起义", "4bjghz": "> （117-065）", "4bkjVW": "description: 张善安，隋末唐初割据势力首领，降唐后又反。", "4blbJy": "[040-039] [[光武帝刘秀|世祖光武皇帝]]上之上建武二年", "4bmCI1": "储宫即东宫，为[[太子]]居所。储宫安定则国本稳固，储宫动荡则朝局不安。[[资治通鉴概述|通鉴]]中\"储宫\"一词常用于讨论[[太子]]地位与继承问题。", "4bmyfX": "陶侃镇武昌是[[东晋]]上[[游军]]事体系形成的关键时期。[[陶侃]]勤于军政，使[[武昌]]成为[[东晋]][[屏障]]上游、震慑[[荆襄]]的[[军事]][[重镇]]。[[陶侃]]死后，[[庾亮]]代镇[[武昌]]，[[东晋]]上[[游军]]政遂为庾氏所控。", "4bnYjP": "description: 李敷，北魏南部尚书，为献文帝所宠任，参豫机密。", "4bnm7f": "> 癸巳，光召丞相、御史、将军、列侯、中二千石、大夫、博士会议未央宫。光曰：“昌邑王行昏乱，恐危社稷，如何？”群臣皆惊鄂失色，莫敢发言，但唯唯而已。田延年前，离席按剑曰：“先帝属将军以幼孤，寄将军以天下，以将军忠贤，能安刘氏也。今群下鼎沸，社稷将倾；且汉之传谥常为‘孝’者，以长有天下，令宗庙血食也。", "4bnmAm": "内庄宅使上言诸州有官租万四千馀斛，上令分给所在充军储。（225-143）", "4bnuGy": "[[李忠义|李宪]]（679—741），[[唐睿宗]][[长子]]，母刘[[皇后]]。睿宗为[[武则天]]所废，宪以[[皇孙]]幽闭。[[唐隆]][[政变]]后，睿宗复位，议立[[太子]]。宪以[[李隆基]]有[[定鼎]]功，让[[太子]]位于隆基（209-070）。宪卒，[[追谥]]让[[皇帝]]。", "4boEpS": "元嘉三年（426年）正月，宋文帝下诏暴徐羡之、傅亮、谢晦杀营阳王（少帝）、庐陵王之罪，命有司诛之。谓\"晦据有上流，或不即罪，朕当亲帅六师为其过防\"。命到彦之、檀道济等发兵讨晦（120-061）。", "4boJDw": "> （155-021）", "4boPI9": "> 使顾成之庙称为太宗，上配太祖，与汉亡极，立经陈纪，为万世法。虽有愚幼、不肖之嗣，犹得蒙业而安。", "4bq2yp": "id: 冒顿", "4bqVoD": "编辑: 裴秀", "4bqlBs": "description: 魏襄王（前318-前296年在位），战国魏国君主。", "4bqrdo": "id: 元欣", "4brDxt": "李茂贞盘踞[[凤翔]]，以岐地为基地，与[[朱温]]长期对峙。[[唐昭宗]]被[[黄巢]]之乱与[[宦官]][[专权]]弄得颠沛[[流离]]，李茂贞趁机控制[[朝廷]]行动，\"[[唐昭宗]]许其承制封拜\"（266-087），获得独立封授的权力。[[李克用]]虽曾逼退其势力，\"克用既去，李茂贞[[骄横]][[如故]]\"（260-071），终究无法根本解决其[[割据]]局面。", "4brmQw": "**条**本义为细长的树枝。引申为条目、条款。亦为地名、爵号，汉代名将[[周亚夫]]封条侯。", "4bt82b": "label: 许士则", "4btX2t": "编辑: 鲁庄公", "4bu9rA": "## 绮罗与奢侈之戒", "4buDZR": "| [[王浚]] | （089-010） | 二月，壬寅，以[[张轨]]为[[太尉]]、[[凉州牧]]，封[[西平公|西平郡公]]；[[王浚]]为大司马、[[都督中外诸军事|都督]]幽、冀诸[[军事]]；荀 |", "4buriF": "label: 太牢", "4bv1FO": "# 下邳", "4bv68V": "新增词条: 禁卫", "4bvEs8": "> 皝追思皇甫真之言，以真为平州别驾。", "4bvF2L": "新增: 汝州", "4bviKv": "以[[兵部侍郎]]曹确[[同平章事]]（250-067）。[[乐工]]李可及善为新声，上以为左威卫[[将军]]。曹确谏曰：\"[[太宗]]定[[文武]]官六百馀员，谓[[房玄龄]]曰'朕以待[[天下]][[贤士]]，工商杂流，不可处也。'\"（250-132）。以曹确充镇海[[节度使]]（252-015）。", "4bw01N": "| 551 | 帅[[巴州刺史]]丹杨[[淳于量]]、[[定州刺史]][[杜龛]]、[[宜州刺史]]王琳、[[郴州]][[齐州刺史|刺史]][[裴之横]]东击景 | （164-023） |", "4bw1KR": "**郓州**为[[南北朝]]至[[唐代]]州名，治所在今[[山东]]郓城，属[[河南道]]。", "4bwyof": "[268-057] 燕主守光遣其将单廷珪将精兵万人出战，与周德威遇于龙头冈。廷珪曰：“今日必擒周杨五以献。”杨五，德威小名也。既战，见德威于陈，援枪单骑逐之，枪及德威背，德威侧身避之，奋楇反击廷珪坠马，生擒，置于军门。燕兵退走，德威引骑乘之，燕兵大败，斩首三千级。廷珪，燕骁将也，燕人失之，夺气。", "4bwyyi": "> 昭王之时，宣太后诱义渠王，杀诸甘泉，遂发兵伐义渠，灭之。", "4bxZCi": "label: 饶阳", "4by6QR": "汉主郭威起兵南下，汴州百官窦贞固等迎于荥阳（287-026）：", "4byyob": "> 子仪至河阳，将谋城守。师人相惊，又奔缺门。诸将继至，众及数万，议捐东京，退保蒲、陕。都虞候张用济曰：“蒲、陕荐饥，不如守河阳，贼至，并力拒之。”子仪从之。使都游弈使灵武韩游瑰将五百骑前趣河阳，用济以步", "4bz5MH": "## 魏文帝称引", "4bzm61": "**上愿**，[[南梁]][[鲜于琛]][[年号]]，自乙卯年（[[公元535年]]），仅数月。", "4bzrr6": "# [[冯延己]]", "4r17t2": "| [[擢孙程]] | （051-017） | 戊午，[[遣使]]者入省，夺得[[玺绶]]，帝乃幸[[嘉德殿]]，遣[[侍御史]][[持节]]收[[阎显]]及其弟[[城门校尉]]耀、执 |", "4r2cs0": "**戍边**，古代士兵守卫边疆的制度。", "4r3BcY": "[[刘渊]]建立[[汉赵|汉国]]后，刘宣等请上尊号，渊依[[汉高祖刘邦|高祖]]称[[汉高祖刘邦|汉王]]故事未即帝位（085-060）。[[石勒]]部落势盛，[[刘琨]]使张儒遣人劝勒归附，勒亦遣董肇奉表于浚请上尊号（089-006）。上尊号之礼往往为劝进仪式，成为权臣[[称帝]]之铺垫。", "4r3sAl": "description: 周朝第32位天子，在位期间正式承认三家分晋，开启战国时代。", "4r3xUi": "surname: 哥舒", "4r4C0l": "新增: 曹英", "4r4O5y": "新增词条：车骑大将军（历任官员表格）", "4r4ccN": "> （125-062）", "4r5s9a": "[286-005] 契丹主入门，民皆惊呼而走。契丹主登城楼，遣通事谕之曰：“我亦人也，汝曹勿惧！会当使汝曹苏息。我无心南来，汉兵引我至此耳。”至明德门，下马拜而后入宫。以其枢密副使刘密权开封尹事。日暮，契丹主复出，屯于赤冈。", "4r6nBx": "| **汉纪年** | [[蜀汉]][[建兴]]十二年 |", "4r6s6W": "张翰为[[齐王]][[司马冏]]东曹掾时，见天下方乱，知冏必败。[[顾荣]]亦在冏府，翰谓之曰\"天下纷纷，祸难未已。夫有[[四海]]之名者，求退良难。吾本[[山林]]间人，无望于时\"，荣抚然。及秋风起，翰思吴中菰菜、莼羹、鲈鱼鲙，叹曰\"人生贵适志耳，富贵何为\"，即弃官归（084-057）。俄而[[齐王冏]]果败，人皆谓翰有先见之明。张翰以莼鲈之思[[辞官]]归隐，为千古文人逸事。\"莼鲈之思\"遂成思乡归隐之典故。", "4r8AXZ": "家丞，古代官职。", "4r8jBa": "[246-075] 上校猎咸阳。", "4rAknH": "# [[公元57年]]", "4rBAt3": "**推举**是古代推[[选举]]荐人才的方式，推举之公与私关乎[[吏治]]清浊。", "4rBJrt": "label: 侍中", "4rCulI": "[[阿史那社尔]]（？—655年），突厥处罗可汗之子，唐代著名蕃将。他早年在西域活动，后因薛延陀强盛而归附唐朝；入唐后任左骁卫大将军，参与征高句丽、讨龟兹等重大战役，以廉洁守纪著称，深得[[唐太宗]]信重，是[[贞观之治|贞观]]年间最重要的蕃将之一。", "4rCw6d": "- [[太安]]二年·[[东海王越]][[起兵]]·[[成汉]]建立", "4rD6UL": "> （034-002）", "4rDDiH": "## 死节", "4rE8m4": "[[祖逖]]死后，祖约继领其部众，拜豫州[[刺史]]。后与[[苏峻]]起兵反晋，兵败奔后赵，为[[石勒]]所杀。", "4rEGkL": "| 550 | 路养妻侄[[南兰陵|兰陵]]萧摩诃 | （163-004） |", "4rEkdO": "description: 唐兵马使", "4rFHVB": "> 苏秦与张仪俱事鬼谷先生，学纵横之术。苏秦自以为不及也。", "4rFVX3": "高允，字伯恭，[[勃海]]蓨人。祖高泰，仕[[后燕]]为[[吏部尚书]]。父高韬，早卒。允少孤，[[好学]]博闻，年十余岁即通经史，为[[州郡]]所重。[[起家]]为郡[[功曹]]，历仕太武、景穆、文成、献文、孝文[[五帝]]，官至[[中书监]]、[[散骑常侍]]，封[[咸阳]]公。[[太和]]十一年（487年）卒，年九十八，赠[[侍中]]、[[司空]]，谥曰文。子[[南阳王绰|高绰]]，[[袭爵]]，官至[[太子洗马]]。允弟高推、高燮等皆知名。允以仁恕简静、历事[[五帝]]五十余年而不失其节，为[[北魏]]文臣中最受敬重的代表[[人物]]。其[[子孙]]虽不及允之显，然[[渤海]]高氏世为[[北朝]][[著姓]]。", "4rFwDe": "刘曜字永明，[[前赵]][[刘渊]]之侄。渊建国称汉，曜为将屡立[[战功]]。[[刘聪]]时，曜攻陷[[洛阳]]（087-073）、[[长安]]（089-010）。聪薨，[[靳准]]作乱，曜[[起兵]]讨准，[[称帝]][[改元]]（091-007）。曜[[徙都]][[长安]]，改国号为赵（092-032），史称[[前赵]]。曜与[[石勒]]交战，兵败被擒杀（093-073）。子[[刘熙|熙]]奔[[上邽]]，为[[石虎]]所灭（094-086）。", "4rGZHu": "[[通鉴]]所载防御之策，重在选将。[[张仁愿]][[筑城]]则[[突厥]]屏息，[[郭知运]]为副使则[[吐蕃]]破胆；裴粲高谈而州城陷，[[张介然]]防御而贼势不可止。防御之要在得人，不在设官之多。", "4rGfnd": "description: 早晨下达的命令到晚上就改变了，形容政令无常、反复不定", "4rHRZf": "[[李暠]]上表言建初二年元日昏雾四塞（118-110）。[[祖冲之]]议[[历法]]上元日度发自虚一（129-111）。[[齐武帝]]太官元日上寿有银酒鎗（140-071）。[[陈宣帝]]御史于元日不劾武官衣剑不齐，帝怒杀之（178-068）。[[武后|武则天]]元日朝指期天泽赦免囚徒（205-076）。[[唐玄宗]]以乾元殿元日受[[朝贺]]（211-132）。[[唐代宗]]元日州府竞为[[贡献]]（226-033）。[[唐文宗]]元日受朝奏[[祥瑞]]皆停（246-010）。", "4rIAd4": "tags: [唐朝, 镇海节度使]", "4rIJS8": "> 每入奏事，坐语移日，所言皆听。荐人或起家至二千石，权移主上。", "4rISzX": "| 550 | 与[[太子]][[左卫将军]]柳敬礼、西[[乡侯]]劝、东[[乡侯]]勔谋[[起兵]]诛王伟。 | （163-087） |", "4rJUEU": "[225-004] 澧朗镇遏使杨猷自澧州沿江而下，擅出境至鄂州，诏听入朝。猷遂溯汉江而上，复州、[[郢州]]皆闭城自守，山南东道节度使梁崇义发兵备之。", "4rKKRt": "长庆四年（824年），穆宗崩，敬宗[[即位]]（243-024）。", "4rKbNU": "> 羊肠在其北，吴起论商纣之地势。", "4rKeYd": "tags: [东汉, 护羌校尉]", "4rKg6u": "[204-094] 丙戌，立武氏七庙于[[洛阳|神都]]，追尊周文王曰始祖文[[皇帝]]，妣姒氏曰文定皇后，平王少子武曰睿祖康皇帝，妣姜氏曰康惠皇后；[[晋阳|太原]]靖王曰严祖成[[皇帝]]，妣曰成庄皇后；赵肃恭王曰肃祖章敬皇帝，魏义康王曰烈祖昭安皇帝，周安成王曰显祖文穆皇帝，忠孝太皇曰太祖孝明高皇帝，妣皆如考谥，称皇后。立武承嗣为[[魏王]]，三思为梁王，攸宁为建昌王，士彟兄孙攸归、重规、载德、攸暨、[[懿宗]]、嗣宗、攸宜、攸望、攸绪、攸止皆为郡王，诸姑姊皆为长公主。", "4rL0tP": "编辑: 张次公", "4rLf5E": "surname: 曾", "4rLokN": "| **纪年** | 赧王五十六年 |", "4rMYQh": "[[袁术]]以下邳陈瑀为[[扬州刺史]]（060-057）。下邳阙宣聚众数千人自称[[天子]]（060-069）。下邳[[陈登]]说[[刘备]]领[[徐州]]（061-028）。[[笮融]]为下邳相大起[[浮屠]]祠（061-060）。[[张飞]]守下邳为曹豹所迎。[[袁术]]遣张勋等步骑数万趣下邳（062-029）。[[曹操]]掘堑围下邳，擒[[吕布]]。", "4rMcnW": "[[隋文帝|隋]]平[[后梁]]，萧琮[[入朝]]，以[[皇后]]萧氏故，甚见亲重，为[[内史令]]，改封[[梁_(概念)|梁]]公，[[宗族]][[缌麻]]以上皆随才擢用（180-080）。[[隋文帝|文帝]]诏以齐、梁、陈宗祀废绝，命高仁英、萧琮、[[陈叔宝]]以时修祭（178-029）。[[窦建德]]问自古[[天子]]降事，[[褚亮]]以\"[[赵佗]]归汉、[[刘禅]]仕晋、近世萧琮至今犹贵\"为对（184-054）。", "4rMgTU": "陆贽尤其强调德宗须以诚感人，不可以刑威独制骄兵：", "4rNCMK": "新建年份条目：前310年", "4rNScn": "description: 倦，疲倦，力竭难继", "4rNfeO": "**翕侯**为古代[[爵位]]名。详见相关人物词条。", "4rO99m": "新建人物词条：徐彦曾", "4rOG0E": "[[蔺相如]]曰王以名使[[赵括]]若胶柱鼓瑟耳（005-042）。[[荆轲]]逐[[秦王]]王环柱而走（007-003）。[[陈胜]]以[[上蔡]]人房君蔡赐为上柱国（007-091）。[[项梁]]渡江矫陈王令拜上柱国（008-020）。[[楚怀王]]孙心立陈婴为上柱国封五县（008-026）。", "4rP3ea": "- [[帷_(概念)|帷]] | [[幕_(概念)|幕]] | [[幄_(概念)|幄]] | [[盖_(概念)|盖]] | [[屏_(概念)|屏]]", "4rP5d1": "> 东武公澹坐不孝徙辽东。九月，征其弟东安王繇复旧爵，拜尚书[[左仆射]]。繇举[[东平王]]楙为平东将军、都督徐州诸军事，镇下邳。", "4rPOTY": "[[北魏]]乐平王丕等至和龙，燕王以牛酒犒军，献甲三千（122-147）。唐末[[田令孜]]以建议幸蜀、收传国宝、散家财犒军为己功（255-042）。[[钱镠]]讨[[董昌]]，昌惧致犒军钱二百万（260-008）。", "4rPr88": "## 军事运输", "4rPxIl": "崔湜通于[[上官昭容]]（婉儿），因昭容之援得以为相，授[[中书侍郎]]、[[平章事|同平章事]]（209-038）。湜与[[郑愔]]俱掌[[吏部]]铨衡，倾附势要，[[赃贿]]狼藉，数外留人，逆用三年阙，时人谓之\"崔郑\"（209-042）。[[唐朝|唐代]][[铨选]][[制度]]至此已坏。崔湜以昭容裙带得相，又以铨衡之权[[纳贿]]鬻官，[[吏治]]之浊，可想而知。湜虽文采出众、才思敏捷，然才胜于德，终为[[小人]]。其一生以文才入仕，以反复升迁，以[[贪浊]]致败：先附[[敬晖]]，背之投三思；三思死，又附[[韦后]]；[[韦后]]败，乃附[[太平公主]]。[[唐玄宗|玄宗]][[即位]]后，湜被[[流放]][[岭南]]，寻[[赐死]]。一介文士，凭才智与钻营屡登相位，终因反复无常而死于非命，其生平恰是[[武周]]至[[开元]]之际廷臣命运的缩影。", "4rQ1Ag": "## 细作与军情", "4rQNxR": "| [[阳王休祐]] | （130-069） | 辛巳，更以山阳王休祐为江州刺史，荆州刺史临海王子顼即留本任。 |", "4rQkvN": "- [[水战]] | [[水军]] | [[舟师]] | [[航海]]", "4rRORA": "| [[徙存审]] | （272-008） | 契丹寇幽州，李克用问帅子郭崇韬，崇韬荐横海节度使李存审。时存审卧病，己卯，徙存审 |", "4rRvN5": "\"重器\"在《[[资治通鉴]]》既指宗庙宝器，亦喻国家权柄。[[孟子]]言齐伐燕毁其宗庙迁其重器（003-025）。[[触龙]]言位尊无功奉厚无劳而挟重器多也（005-029）。[[汉明帝]]言天下重器常恐不任（043-084）。[[杜乔]]言无功小人有官爵非爱民重器（052-011）。[[胡广]]言天下重器诚知当详择其人（053-007）。为古代政治之重要比喻。", "4rSCaH": "爱州为[[唐朝|唐代]][[岭南道]]属州，治所在今越南清化。", "4rTIvS": "崔郸以[[太常]]卿同[[中书]][[门下]]平章事（246-032）。武宗欲诛[[刘弘]]逸等，德裕与[[崔珙]]、崔郸、[[陈夷行]]三上奏[[谏止]]，又邀[[枢密使]]至[[中书]]，使入奏（246-064）。后罢相，以[[同平章事]]充[[西川]][[节度使]]（246-078）。", "4rTLvs": "**钲**，古乐器，形似钟，军中以[[钲鼓]]号令。", "4rTpwR": "[[司马光]]通过徐晃，展示了曹魏五子良将体系中\"全才将领\"的形象：既能奇袭又能守备，既有战术敏锐又有战略眼光，以严格军纪著称于三军，是[[曹操]]最信赖的独当一面型大将之一。", "4rUVBu": "[[司马光]]通过刘知远的记录，展示了五代乱世中英雄豪杰凭借个人信义与军事实力迅速崛起的历史规律。刘知远在位不足一年即病逝，后汉传子刘承祐，不久被[[郭威]]所代，建立后周。", "4rVCAA": "| 264 | 邓艾本营将士追出艾于槛车，迎还。卫瓘自以与会共陷艾，恐其为变，乃遣护军 | （078-047） |", "4rVNiO": "[[班固]]谓汉成帝时公卿奏议可述，遭世承平上下和睦（033-009）。五宫中郎将线纯与太仆[[朱浮]]奏议礼制，以先帝四庙代亲庙（043-073）。", "4rVb7x": "> 汉王将数十万之众，距巩、雒，阻山河之险，一日数战，无尺寸之功，折北不救。", "4rVldx": "[201-144] 郭待封先与薛仁贵并列，及征吐蕃，耻居其下，仁贵所言，待封多违之。军至[[大非川]]，将趣乌海，仁贵曰：“乌海险远，军行甚难，辎重自随，难以趋利；宜留二万人，为两栅于大非岭上，辎重悉置栅内，吾属帅轻锐，倍道兼行，掩其未备，破之必矣。”仁贵帅所部前行，击吐蕃于河口，大破之，斩获甚众，进屯乌海以俟待封。待封不用仁贵策，将辎重徐进，未至乌海，遇吐蕃二十馀万，待封军大败，还走，悉弃辎重。仁贵退屯大非川，吐蕃相论钦陵将兵四十馀万就击之，唐兵大败，死伤略尽。仁贵、待封与阿史那道真并脱身免，与钦陵约和而还。敕大司宪乐彦玮即军中按其败状，械送京师，三人皆免死除名。", "4rW79I": "label: 陛下", "4rWfbn": "> [[秦王]]会[[楚王]]于宛，会赵王于中阳。", "4rWfeu": "太子洗马，古代官职。", "4rWin1": "[[霍光]][[出入]][[禁闼]]二十馀年，出则奉车，入侍[[左右]]，小心谨慎（022-088）。入侍以亲信为本。", "4rWsmW": "description: 后唐李继韬之弟，奔梁请以泽潞为臣，李继韬死后劝兄不成，终被斩", "4rXFhi": "[[司马迁]]论[[游侠]]皆有绝异之姿惜不入于[[道德]]（018-071）。[[赵飞燕]]姿性尤醲粹（031-037）。傅喜姿性端悫[[论议]]忠直（035-030）。[[陈留]]令刘豫以[[刻薄]]之姿务为严苦（046-021）。[[孙策]]为人[[美姿]]颜能笑语（061-055）。[[周瑜]]论[[刘备]]以[[枭雄]]之姿有[[关羽]][[张飞]]熊虎之将（066-017）。", "4rXLgl": "description: 陕县，战国魏地，汉属弘农郡，在崤函之东。", "4rXt6y": "> 百姓闻孙郎至，皆失魂魄。", "4rXzvU": "tags: [制度, 官制, 俸禄]", "4rY4Sl": "> 宇文泰为三军所推，居百二之地，所谓己操戈矛，宁肯授人以柄！", "4rYAB4": "腰为腰部。[[李斯]]被[[赵高]]陷害，论[[腰斩]][[咸阳]]市（008-035）。[[汉武帝]]诛[[方士]][[栾大]]，坐[[诬罔]][[腰斩]]（020-068）。[[马廖]][[上疏]]引谚\"[[楚王]]好细腰，[[宫中]]多饿死\"劝[[朝廷]]改政移风（046-017）。[[冯定]]坐[[腰斩]]（051-077）。[[梁冀]][[腰斩]][[辽东]][[太守]]侯猛（054-026），又[[鸩杀]][[荆州]][[刺史]]。[[诸葛恪]]被诛后以苇席裹尸篾束腰投之石子冈（076-021）。[[张华]]被[[贾充]]以[[腰斩]]相威胁（081-015）。", "4rYGOZ": "| 元始五年 | 泉陵侯刘庆上书言：“周成王幼少 | （036-035） |", "4rYXmr": "description: 左屯卫将军，古代官职。", "4rZlaY": "**货财**为古代货物与[[钱财]]的统称，指[[社会]]财富积累。《[[资治通鉴概述|通鉴]]》中\"货财\"描述[[府库]]充盈的[[经济]]繁荣景象，亦指[[赏赐]][[贿赂]]之物。", "4rZuTQ": "[[桓玄]]攻[[历阳]]，襄城[[太守]][[司马休之]]婴城[[固守]]（112-063）。后休之与[[刘敬宣]]、[[高雅之]]等奔[[洛阳]]，欲借秦兵复晋（112-074）。又谋结[[青州]]大姓杀[[南燕]]主[[慕容备德|备德]]，推休之为主，不克（113-071）。", "4ra2Qv": "[[北魏]]以[[上党]]王[[元天穆|天穆]]为[[大将军]]、[[开府]]仪同[[三司]]，世袭[[晋阳|并州]][[刺史]]（152-061）。尔硃兆辞天柱称号，后加[[都督]]十州诸军事，世袭[[晋阳|并州]][[刺史]]（155-018）。", "4ranim": "编辑: 义帝", "4rbAII": "| 841 | 知枢密刘弘逸、薛季陵宠于文宗 | （246-064） |", "4rbbUA": "description: 汉顺帝第三个年号（142—144），共三年", "4rbtRg": "| [[前将军刘丰]] | （088-029） | 粲、曜送尚书卢志、侍中许遐、太子右卫率崔玮于平阳。聪复以曜为车骑大将军，以前将军 |", "4rc2vf": "> 匡国节度使刘知俊邀击坊州之兵，斩首三千馀级，擒坊州刺史刘彦晖。", "4rdKp3": "[160-045] 澄疑咨议温子升知瑾等谋，方使之作献武王碑，既成，饿于[[晋阳]]狱，食弊襦而死。弃尸路隅，没其家口，太尉长史宋游道收葬之。澄谓游道曰：“吾近书与京师诸贵，论及朝士，以卿僻于朋党，将为一病。今乃知卿真是重故旧、尚节义之人，天下人代卿怖者，是不知吾心也。”九月，辛丑，澄还[[晋阳]]。", "4reEXE": "| [[杨初|仇池公]] | 杨初 | 337—355 | 毅之族弟 |", "4reQeX": "> 帝欲诛樊爱能等以肃军政，犹豫未决。己亥，昼卧行宫帐中，张永德侍侧，帝以其事访之，对曰“爱能等素无大功，忝冒节钺，望敌先逃，死未塞责。且陛下方欲削平四海，苟军法不立，虽有熊罴之士，百万之众，安得而用之！”帝掷枕于地，大呼称善。即收爱能、徽及所部军使以上七十馀人。责之曰：“汝曹皆累朝宿将，非不能战。今望风奔遁者，无他，正欲以朕为奇货，卖与刘崇耳！”悉斩之。", "4recJG": "[093-028] 有司奏：“王彬等敦之亲族，皆当除名。”诏曰：“司徒导以大义灭亲，犹将百世宥之，况彬等皆公之近亲乎！”悉无所问。", "4rfDpz": "> 己亥，【朝集】使利州都督武士彟等复上表请封禅，不许。", "4rfQxA": "description: 江淮，长江与淮河之间的地区，南北朝以来为南北争夺之要域。", "4rgFtb": "description: 天德（544—548年），梁朝交州李贲年号。李贲称越帝，置百官。", "4rh7F3": "[[北魏]]道[[武帝]]斥僧徒侵渔[[百姓]]取材为惠，未合布施之道（107-087）。[[傅奕]]上疏斥[[佛教]]\"布施万钱希万倍之报，持斋一日冀百日之粮\"（191-094）。[[周世宗]]以佛志在利人，虽[[头目]]犹舍以布施，若朕身可以济民亦非所惜（292-055）。布施自[[佛教]]入华后成为[[中国]]社会慈善之重要方式。", "4rhHyE": "黑色在[[汉代]]官服中为皂隶所服，地位较低。[[资治通鉴概述|通鉴]]所见黑帜、黑衣、黑马等，在[[军事]]记号和等级标识中各有其义。", "4rhLuC": "宋光嗣与[[景润澄]]等被[[王宗弼]][[矫命]]斩杀（274-009）：", "4rhVAm": "编辑: 危全讽", "4rhgA6": "# [[凤翔尹]]", "4rhptU": "> （049-039）", "4riL84": "### 再击柔然", "4rieHV": "> 上遣推讷，得其赃贿，竟致于法；敕委夫人招慰亡叛。", "4riiHv": "| [[卫将军谢安]] | （105-050） | 三月，以[[卫将军]][[谢安]]为太保。 |", "4rkSSo": "[[魏文侯]]欲以李克为将伐秦，李克以[[吴起]]为更合适的将才举荐，并评价[[吴起]]\"贪而好色，然[[用兵]]，[[司马]][[穰苴]]弗能过也\"（001-016）。李克的推荐眼光极准，[[吴起]]果然成为[[战国]]最杰出的[[军事]][[统帅]]之一。", "4rkcnK": "新增: 雍州", "4rkd8U": "[[傅介子]]为[[骏马监]]，使[[大宛]]，诏令责[[楼兰]]、[[龟兹]]王，二王皆谢服（023-068）。介子从大宛还，至龟兹，率其吏士诛斩[[匈奴]]使者。复奉使刺楼兰王安归，持首还诣阙，公卿将军议嘉其功，封义阳侯，食邑七百户（023-070）。傅介子以三十六人立功[[西域]]，与[[陈汤]]斩[[郅支]]并称西汉使臣立功绝域之典范。", "4rlTSr": "新建年份条目：公元77年", "4rm1ct": "| 212 | ”程昱曰：“此乃扰攘之际 | （066-036） |", "4rmGdZ": "| 742 | [[长安令]]韦坚为陕郡[[魏郡太守|太守]] | （215-010） |", "4rnp1x": "编辑: 五色", "4rotIN": "id: 姚裕", "4rp9YG": "| 864 | 忠武大将颜庆复请筑新安、遏戎二城 | （250-081） |", "4rpDoU": "| **[[资治通鉴概述|通鉴]]卷目** | [[第220卷]] · 唐纪 |", "4rpVUm": "[102-055] 猛望燕兵之众，谓邓羌曰：“今日之事，非将军不能破勍敌。成败之机，在兹一举，将军勉之！”羌曰：“若能以司隶见与者，公勿以为忧。”猛曰：“此非吾所及也，必以安定太守、万户侯相处。”羌不悦而退。俄而兵交，猛召羌，羌寝弗应。猛驰就许之，羌乃大饮帐中，与张蚝、徐成等跨马运矛，驰赴燕陈；出入数四，旁若无人，所杀伤数百。及日中，燕兵大败，俘斩五万馀人，乘胜追击，所杀及降者又十万馀人，评单骑走还鄴。", "4rpYdu": "| [[杨难敌|仇池公]] | 杨难敌 | 317—334 | 茂搜之子 |", "4rplJt": "| [[章事卢文纪]] | （280-068） | 庚子，以唐[[中书侍郎]]、[[同平章事]]卢文纪为吏部尚书。以[[皇城]]使[[晋阳]][[周瑰]]为[[大将军]]、充[[三司使]] |", "4rq3G7": "| [[可硃浑道元]] | （160-022） | 甲辰，东魏以开府仪同三司库狄干为太师，录尚书事孙腾为太傅，汾州刺史贺拔仁为太保， |", "4rqnAE": "提升拥旄质量档位至standard", "4rqzcV": "冉闵字永曾，小字棘奴，[[魏郡]]内黄人。父冉瞻，为[[后赵]]石虎养孙，故闵又名石闵（094-069）。闵为石虎养孙，勇悍善战。石虎薨，诸子争立，闵诛杀石氏，屠羯人二十馀万（099-067），自立为帝，国号魏，都[[邺城]]（099-069）。闵与[[前燕]]慕容儁战，兵败被执，斩于龙城（099-071）。冉魏灭。", "4rrND8": "> （238-034）", "4rrNwU": "- 风", "4rs4LO": "阳关在《[[资治通鉴概述|资治通鉴]]》中既是[[军事]]关隘也是[[文明]]的界标。[[汉武帝]]通[[西域]]凡三[[十六国]]，东接[[玉门关|汉玉门]]、阳关，西限葱岭（020-036）——阳关为[[汉]]疆之西极，与[[玉门关]]分扼[[西域]]南北二道，阳关道经[[鄯善]]、[[于阗]]至葱岭，是[[丝绸之路]]南道的起点。[[郑吉]]为[[西域都护]]治乌垒城，去阳关二千七百馀里（026-034）——阳关至[[乌垒]]的距离丈量了[[汉]]朝在[[西域]]的[[治理]]纵深，二千七百里既是[[地理]]的距离也是[[帝国]]意志的[[尺度]]。[[东汉]]时北[[匈奴]]与[[车师]][[入寇]][[河西]]，议者欲闭[[玉门关|玉门]]、阳关以绝其患（050-118）——议闭阳关反映出[[东汉]][[朝廷]]对[[西域]]的退缩倾向，[[西域]]之弃与守成为[[东汉]][[外交]]政策的反复主题。[[前秦]][[苻坚]]遣[[石越]]出[[鲁阳]]关寇[[襄阳]]（104-035），阳关之名亦见于[[十六国]]征战之中。[[春秋]]时鲁伐齐入阳关（001-102），是阳关在[[资治通鉴概述|通鉴]]中的最早出现——此鲁地之阳关与[[敦煌]]之阳关同名而异地，反映了\"阳关\"[[作为]][[关隘]]通名的普遍性。然而后世言阳关，必以[[敦煌]]为归——\"西出阳关无故人\"的[[诗意]]使阳关成为[[中原]]与[[西域]]的文化分界。", "4rs74t": "**贤**，[[贤德]]。贤者更礼为[[变法]]之基，贤不肖别为[[才德论|才德之辨]]。", "4rsGU6": "id: 亩", "4rshEX": "[[高仙芝]]入朝后，封常清接掌安西，\"以安西[[行军]]司马【封常清】为安西四镇[[节度使]]\"（216-102），进而又领北庭事务，\"以【封常清】权北庭都护、伊西[[节度使]]\"（217-013），并南征大勃律，\"安西[[节度使]]【封常清】击大勃律，至菩萨劳城，前锋屡捷\"（216-125），扩展唐朝在中亚的控制。", "4rsnV3": "[[范雎]]入秦后欲报仇，[[魏齐]]出逃藏匿于平原君家中（005-023）。[[秦王]]为报[[范雎]]之仇，\"乃为好言诱平原君至秦而执之。[[遣使]]谓[[王镕|赵王]]曰：'不得齐首，吾不出王弟'\"（005-049）。平原君因庇护友人而遭[[秦国]]要挟，陷入两难困境，折射出[[战国]]外交的残酷本质。", "4rtF2G": "- [[淡]] | [[厚]] | [[稠]]", "4rtfQy": "左内史，古代[[官职]]。", "4ru1Jk": "甄琛为河南尹，与处士冯亮择嵩山形胜之地立闲居寺，极岩壑土木之美，远近承风，无不事佛（147-051）。魏主命黄门侍郎甄琛驰驲锁败军之将元昶，穷其败状，琛据实奏闻，昶与赵遐皆免官（147-073）。琛又表称国家居代患多盗窃，广置主司里宰，皆以下代令长及五等散男有经略者乃得为之（147-076）。", "4ru4cM": "[[张仪]]说燕王，言秦下甲云中、[[九原]]，驱赵而攻燕，则易水长城非燕之有（003-037）。[[赵武灵王]]欲从云中、[[九原]]南袭咸阳（003-083）。赵置云中、[[雁门]]、代郡以拒胡（006-057）。汉初以云中、[[雁门]]、代郡封兄宜信侯喜为代王（011-036）。[[周勃]]悉定代郡、[[雁门]]、云中地，斩陈豨于当城（012-045）。云中自古为北疆要地，农耕与游牧在此交汇，历代兵家必争。", "4ruELk": "## 历职太守詹事", "4ruJkc": "[[贞观之治|贞观]]九年春，[[李靖]]以[[西海道]][[行军]]大[[总管]]，率[[侯君集]]、[[李道宗]]、[[李大亮]]等[[分路]]出击。[[李道宗|任城王]][[李道宗]]败[[吐谷浑]]于库山。伏允悉烧野草，轻兵走入碛中，企图以[[坚壁清野]]困唐军。诸将以为马无草不可深入，[[侯君集]]力主[[追击]]（194-070）。", "4ruNuB": "label: 萧", "4ruVzh": "黄宪为东汉中晚期名士，虽隐居不仕，而名重当时。郭林宗称其\"汪汪若千顷陂，澄之不清，淆之不浊\"。其高洁品行为汉末清议所推崇。", "4rv5mT": "id: 山（姓氏）", "4rv8OA": "label: 深堑", "4rwVO3": "新增: 将作大匠", "4rwvHZ": "[184-018] 八月，己卯，雨霁。庚辰，[[唐高祖|李渊]]命军中曝铠仗行装。辛巳旦，[[东南]]由山足细道趣霍邑。渊恐宋老生不出，[[李建成]]、[[唐太宗|李世民]]曰：“老生勇而无谋，以轻骑挑之，理无不出；脱其固守，则诬以贰于我。彼恐为左右所奏，安敢不出！”渊曰：“汝测之善，老生不能逆战贾胡，吾知其无能为也！”渊与数百骑先至霍邑城东数里以待[[步兵]]，使建成、世民将数十骑至城下，举鞭指麾，若将围城之状，且诟之。老生怒，引兵三万自东门、南门分道而出，渊使殷开山趣召后军。后军至，渊欲使军士先食而战，世民曰：“时不可失。”渊乃与建成陈于城东，世民陈于城南。渊、建成战小却，世民与军头临淄段志玄自南原引兵驰下，冲老生陈，出其背，世民手杀数十人，两刀皆缺，流血满袖，洒之复战。渊兵复振，因传呼曰：“已获老生矣！”老生兵大败，渊兵先趣其门，门闭，老生下马投堑，刘弘基就斩之，僵尸数里。日已暮，渊即命登城，时无攻具，将士肉薄而登，遂克之。", "4ryCyI": "\"六艺\"本义为周代官学教育的六门课程：**礼**（[[礼仪]]）、**乐**（[[音乐]]）、**射**（射箭）、**御**（驾车）、**书**（书写）、**数**（算术）。[[孔子]]以六艺授徒，培养出[[七十二贤]]，[[开平]]民教育之先河。后世遂以六艺代指[[儒家]]经典体系。", "4ryLAo": "田弘正以[[归附]]改变了[[藩镇]]格局，\"及吉甫入相，【田弘正】以魏博[[归附]]。吉甫以为[[汝州]]扞蔽[[洛阳|东都]]，[[河阳]]宿兵，本以制魏博，今弘正[[归附]]……\"（239-034），[[李吉甫]]在田弘正[[归附]]后重新谋划各道的战略部署，魏博主动[[归顺]]成为[[元和中兴]]的重要转折点。", "4rySYo": "description: 齐襄王（前283-前265年在位），田单复国后即位之齐王。", "4rycVj": "- 盘", "4ryjEJ": "description: 姓「沙」的历史人物列表，共 2 人。", "4rzSZG": "label: 大雾", "4rzZX3": "> （069-081）", "4rzlLt": "王常劝说诸将立[[刘縯]]为帝，虽未成功，但表明了对刘氏[[兄弟]]的支持。在[[昆阳之战]]中，王常率军[[力战]]，大破[[王莽]]军。", "4rzlOS": "id: 康愔", "4rzrTq": "description: 公元167年，汉桓帝永康元年。无大事记载。"}